{
  "format": "SGO",
  "endian": "LE",
  "variables": [
    {"type": "string", "value": "AF14", "name": "WeaponName_AssultRifle01"},
    {
      "type": "string",
      "value": "!     Capacity: 120   \n! Rate of Fire: 12.0/sec\n!       Damage: 10.0    \n!  Reload Time: 1.5sec  \n!        Range: 150.0m \n!     Accuracy: B         \n\nA high-powered, fully automatic rifle. Developed in 2011, this new model boasts considerably higher fire power than the original. The special rounds it fires can easily penetrate heavy steel.",
      "name": "WeaponText_AssultRifle01"
    },
    {"type": "string", "value": "AF14-RA", "name": "WeaponName_Weapon001"},
    {
      "type": "string",
      "value": "!     Capacity: 200   \n! Rate of Fire: 30.0/sec\n!       Damage: 6.0     \n!  Reload Time: 2.5sec  \n!        Range: 120.0m \n!     Accuracy: B         \n\nAn upgraded version of the AF14. This RA model has an improved rate of fire and can instantly riddle a target full of bullets. Range is sacrificed in exchange.",
      "name": "WeaponText_Weapon001"
    },
    {"type": "string", "value": "AF14-ST", "name": "WeaponName_Weapon002"},
    {
      "type": "string",
      "value": "!     Capacity: 10    \n! Rate of Fire: 3.0/sec\n!       Damage: 70.0    \n!  Reload Time: 1.5sec  \n!        Range: 250.0m \n!     Accuracy: A+        \n\nAn ST model AF14 upgrade that sacrifices firing speed for power and range. However, since it is the first ST model developed, shots travel slowly, making it ineffective against fast-moving targets.",
      "name": "WeaponText_Weapon002"
    },
    {"type": "string", "value": "AF14-RAR", "name": "WeaponName_Weapon003"},
    {
      "type": "string",
      "value": "!     Capacity: 150   \n! Rate of Fire: 60.0/sec\n!       Damage: 5.4     \n!  Reload Time: 2.0sec  \n!        Range: 120.0m \n!     Accuracy: B         \n\nAn upgraded AF14-RA that fires an incredible 60 shots per second, resulting in overwhelming damage when all rounds hit. Ammunition, however, is used up quickly, and the weapon must be reloaded frequently. Also has a short range.",
      "name": "WeaponText_Weapon003"
    },
    {"type": "string", "value": "AF14-B3", "name": "WeaponName_Weapon004"},
    {
      "type": "string",
      "value": "!     Capacity: 30          Zoom: 2.0x  \n! Rate of Fire: 2.0×3/sec\n!       Damage: 40.0    \n!  Reload Time: 1.5sec  \n!        Range: 240.0m \n!     Accuracy: A-        \n\nAn upgraded AF14.  This model fires 3-shot bursts in place of the full-auto function. There is no recoil from rapid-fire shots, so accuracy is unaffected. Range is also improved. \n(This weapon has no auto-fire)",
      "name": "WeaponText_Weapon004"
    },
    {"type": "string", "value": "AF15", "name": "WeaponName_AssultRifle_18K"},
    {
      "type": "string",
      "value": "!     Capacity: 120   \n! Rate of Fire: 12.0/sec\n!       Damage: 17.0    \n!  Reload Time: 1.5sec  \n!        Range: 138.0m \n!     Accuracy: B         \n\nA new, vastly improved AF series model with firepower almost double that of the AF14. Range is only slightly decreased in exchange.",
      "name": "WeaponText_AssultRifle_18K"
    },
    {"type": "string", "value": "AF15-ST", "name": "WeaponName_Weapon005"},
    {
      "type": "string",
      "value": "!     Capacity: 8     \n! Rate of Fire: 3.0/sec\n!       Damage: 105.0   \n!  Reload Time: 1.5sec  \n!        Range: 256.0m \n!     Accuracy: A+        \n\nThis ST model AF15 sacrifices firing rate for power. It cannot fire rapidly, but has great firepower and doubled range.  Additionally, the slow shot speed typical of ST models has been remedied, making this an effective weapon against fast moving targets as well.",
      "name": "WeaponText_Weapon005"
    },
    {"type": "string", "value": "AF16", "name": "WeaponName_Weapon006"},
    {
      "type": "string",
      "value": "!     Capacity: 100   \n! Rate of Fire: 12.0/sec\n!       Damage: 23.0    \n!  Reload Time: 1.5sec  \n!        Range: 180.0m \n!     Accuracy: B         \n\nA new AF series model. With improved firepower and vastly increased range, this weapon is extremely effective in mid-range combat. Ammo capacity is slightly decreased in exchange.",
      "name": "WeaponText_Weapon006"
    },
    {"type": "string", "value": "AF-V", "name": "WeaponName_Weapon007"},
    {
      "type": "string",
      "value": "!     Capacity: 105   \n! Rate of Fire: 12.0/sec\n!       Damage: 12.0×2 \n!  Reload Time: 1.5sec  \n!        Range: 180.0m \n!     Accuracy: B+        \n\nA special AF series model. This assault rifle combines two guns to fire 2 bullets simultaneously in a V pattern.",
      "name": "WeaponText_Weapon007"
    },
    {"type": "string", "value": "AF16-RA", "name": "WeaponName_Weapon008"},
    {
      "type": "string",
      "value": "!     Capacity: 200   \n! Rate of Fire: 30.0/sec\n!       Damage: 12.0    \n!  Reload Time: 2.5sec  \n!        Range: 120.0m \n!     Accuracy: C         \n\nThis coveted AF16 upgrade boasts an improved rate of fire without sacrificing power. Accuracy, however, is severely decreased in exchange, giving it more of a shotgun-like feel.",
      "name": "WeaponText_Weapon008"
    },
    {"type": "string", "value": "AF17", "name": "WeaponName_Weapon009"},
    {
      "type": "string",
      "value": "!     Capacity: 120   \n! Rate of Fire: 12.0/sec\n!       Damage: 26.0    \n!  Reload Time: 1.5sec  \n!        Range: 180.0m \n!     Accuracy: B         \n\nA new AF series model. This superb weapon features improved firepower. It no longer suffers from poor ammo capacity and has excellent overall balance.",
      "name": "WeaponText_Weapon009"
    },
    {"type": "string", "value": "AF18", "name": "WeaponName_Weapon010"},
    {
      "type": "string",
      "value": "!     Capacity: 120   \n! Rate of Fire: 15.0/sec\n!       Damage: 30.0    \n!  Reload Time: 2.0sec  \n!        Range: 80.0m  \n!     Accuracy: B         \n\nA new AF series model developed primarily for a high bullet velocity, making it possible to aim accurately at agile enemies. Range, on the other hand, is extremely short.",
      "name": "WeaponText_Weapon010"
    },
    {"type": "string", "value": "AF18-RA", "name": "WeaponName_Weapon011"},
    {
      "type": "string",
      "value": "!     Capacity: 250   \n! Rate of Fire: 30.0/sec\n!       Damage: 18.0    \n!  Reload Time: 2.5sec  \n!        Range: 150.0m \n!     Accuracy: A+        \n\nThis rapid-firing AF18 upgrade does not suffer from the short range of other RA models. The AF18's high velocity is somewhat compromised, but it has excellent overall balance. Accuracy is also improved, given a skilled hand.",
      "name": "WeaponText_Weapon011"
    },
    {"type": "string", "value": "AF18-X", "name": "WeaponName_Weapon012"},
    {
      "type": "string",
      "value": "!     Capacity: 140   \n! Rate of Fire: 12.0/sec\n!       Damage: 50.0    \n!  Reload Time: 2.0sec  \n!        Range: 150.0m \n!     Accuracy: E         \n\nA special AF18 model developed primarily for firepower. It is nearly twice as powerful as the AF18 but accuracy has been severely compromised, making this weapon feel more like a shotgun.",
      "name": "WeaponText_Weapon012"
    },
    {"type": "string", "value": "AF19-ST", "name": "WeaponName_Weapon013"},
    {
      "type": "string",
      "value": "!     Capacity: 10    \n! Rate of Fire: 4.0/sec\n!       Damage: 230.0   \n!  Reload Time: 1.5sec  \n!        Range: 300.0m \n!     Accuracy: A+        \n\nAn upgraded ST model AF19 that sacrifices rate of fire for power. Power, accuracy, and range are all very high. It can also be said to have the fastest bullet velocity of any assault rifle.",
      "name": "WeaponText_Weapon013"
    },
    {"type": "string", "value": "AF19", "name": "WeaponName_Weapon014"},
    {
      "type": "string",
      "value": "!     Capacity: 120         Zoom: 2.0x  \n! Rate of Fire: 15.0/sec\n!       Damage: 44.0    \n!  Reload Time: 1.5sec  \n!        Range: 150.0m \n!     Accuracy: B+        \n\nThis new AF series model has no outstanding strong point, but successfully improves on firepower without sacrificing overall performance. It is a great weapon with no particular disadvantages.",
      "name": "WeaponText_Weapon014"
    },
    {"type": "string", "value": "AF19-RA", "name": "WeaponName_Weapon015"},
    {
      "type": "string",
      "value": "!     Capacity: 250   \n! Rate of Fire: 30.0/sec\n!       Damage: 33.0    \n!  Reload Time: 5.0sec  \n!        Range: 200.0m \n!     Accuracy: B+        \n\nThis upgraded RA model AF19 no longer suffers from short range. In fact, it has a longer range than the standard AF19. However, it uses a special magazine that takes slightly longer to reload.",
      "name": "WeaponText_Weapon015"
    },
    {"type": "string", "value": "AF19X-B3", "name": "WeaponName_Weapon016"},
    {
      "type": "string",
      "value": "!     Capacity: 120         Zoom: 2.0x  \n! Rate of Fire: 2.0×3/sec\n!       Damage: 150.0   \n!  Reload Time: 1.5sec  \n!        Range: 247.5m \n!     Accuracy: B         \n\nDeveloped for greater firepower, this AF19 upgrade features a wider barrel. Full-auto fire has been replaced with a 3-shot burst to suppress the greater recoil.\n(This weapon has no auto-fire)",
      "name": "WeaponText_Weapon016"
    },
    {"type": "string", "value": "AF20", "name": "WeaponName_Weapon017"},
    {
      "type": "string",
      "value": "!     Capacity: 140   \n! Rate of Fire: 12.0/sec\n!       Damage: 92.0    \n!  Reload Time: 2.0sec  \n!        Range: 180.0m \n!     Accuracy: A-        \n\nThis new AF series model is considerably improved all around. Range is increased as well.",
      "name": "WeaponText_Weapon017"
    },
    {"type": "string", "value": "AF20-ST", "name": "WeaponName_Weapon018"},
    {
      "type": "string",
      "value": "!     Capacity: 5     \n! Rate of Fire: 4.0/sec\n!       Damage: 1200.0  \n!  Reload Time: 5.0sec  \n!        Range: 400.0m \n!     Accuracy: S+        \n\nAn ST model AF20 that sacrifices rate of fire for outstanding firepower and bullet velocity. The trade-offs are a reduced ammo capacity and a longer reload time.",
      "name": "WeaponText_Weapon018"
    },
    {"type": "string", "value": "AF20-RAR", "name": "WeaponName_Weapon019"},
    {
      "type": "string",
      "value": "!     Capacity: 999   \n! Rate of Fire: 60.0/sec\n!       Damage: 26.0    \n!  Reload Time: 3.0sec  \n!        Range: 140.0m \n!     Accuracy: B         \n\nThis RAR model AF20 upgrade boasts the fastest rate of fire, clearly surpassing that of RA models. Additionally, magazine capacity has been greatly increased by minimizing bullet size.",
      "name": "WeaponText_Weapon019"
    },
    {"type": "string", "value": "AF21-B4", "name": "WeaponName_Weapon020"},
    {
      "type": "string",
      "value": "!     Capacity: 140   \n! Rate of Fire: 2.0×4/sec\n!       Damage: 210.0   \n!  Reload Time: 3.0sec  \n!        Range: 260.0m \n!     Accuracy: A+        \n\nAn AF20 upgrade. This model exchanges full-auto fire for a burst mechanism to improve accuracy. The resulting reduction in recoil also enables greater precision.\n(This weapon has no auto-fire)",
      "name": "WeaponText_Weapon020"
    },
    {"type": "string", "value": "AF99", "name": "WeaponName_Weapon021"},
    {
      "type": "string",
      "value": "!     Capacity: 160         Zoom: 2.0x  \n! Rate of Fire: 15.0/sec\n!       Damage: 140.0   \n!  Reload Time: 2.0sec  \n!        Range: 240.0m \n!     Accuracy: A         \n\nThe masterpiece of the AF series. This model achieves the maximum balance of power, range and accuracy possible, making it a formidable weapon in close and mid-range combat.",
      "name": "WeaponText_Weapon021"
    },
    {"type": "string", "value": "AF99-ST", "name": "WeaponName_Weapon022"},
    {
      "type": "string",
      "value": "!     Capacity: 20    \n! Rate of Fire: 4.0/sec\n!       Damage: 700.0   \n!  Reload Time: 3.0sec  \n!        Range: 480.0m \n!     Accuracy: S+        \n\nThis upgraded AF99 sacrifices firing rate for power like other ST models, but no longer suffers from the low ammo capacity and long reload times of its predecessors. Range has also been extended, making it a most effective mid-long range weapon.",
      "name": "WeaponText_Weapon022"
    },
    {"type": "string", "value": "AF100", "name": "WeaponName_Weapon023"},
    {
      "type": "string",
      "value": "!     Capacity: 180         Zoom: 2.0x  \n! Rate of Fire: 15.0/sec\n!       Damage: 160.0   \n!  Reload Time: 2.0sec  \n!        Range: 264.0m \n!     Accuracy: A         \n\nThe ultimate assault rifle, created with Ravager technology. This weapon pushes all attributes to the max. Bullet velocity is particularly improved, making it possible to fire accurately at fast-moving targets with steady aim.",
      "name": "WeaponText_Weapon023"
    },
    {"type": "string", "value": "Buffalo G1", "name": "WeaponName_Shotgun_SG4"},
    {
      "type": "string",
      "value": "!     Capacity: 8     \n! Rate of Fire: 1.0/sec\n!       Damage: 19.0×10\n!  Reload Time: 4.0sec  \n!        Range: 130.0m \n!     Accuracy: B-        \n\nThis combat shotgun fires dozens of rounds per shot. These rounds scatter over a wide area, making it easy to hit fast-moving enemies. The weapon also deals tremendous damage at close range. Drawbacks are its short range and slow reload time.",
      "name": "WeaponText_Shotgun_SG4"
    },
    {"type": "string", "value": "Buffalo G2", "name": "WeaponName_Weapon024"},
    {
      "type": "string",
      "value": "!     Capacity: 8     \n! Rate of Fire: 1.0/sec\n!       Damage: 15.0×20\n!  Reload Time: 4.0sec  \n!        Range: 72.0m  \n!     Accuracy: C         \n\nA new Buffalo shotgun that fires twice as many shells, greatly increasing its firepower. Rounds are dispersed over a wider area, but a very short range makes this an even more close-range weapon. The pump-action of this model also means a long reload time.",
      "name": "WeaponText_Weapon024"
    },
    {"type": "string", "value": "Governor 25", "name": "WeaponName_Weapon025"},
    {
      "type": "string",
      "value": "!     Capacity: 8     \n! Rate of Fire: 1.0/sec\n!       Damage: 18.0×25\n!  Reload Time: 4.0sec  \n!        Range: 72.0m  \n!     Accuracy: D         \n\nA powerful shotgun that fires 25 shots over a wide area, making it possible to hit several enemies at once. It also has high firepower, and can deal unrivaled damage when all shots hit. However, because it covers a wide area, its range is that much shorter.",
      "name": "WeaponText_Weapon025"
    },
    {"type": "string", "value": "Wideshot", "name": "WeaponName_Weapon026"},
    {
      "type": "string",
      "value": "!     Capacity: 8     \n! Rate of Fire: 1.0/sec\n!       Damage: 22.0×20\n!  Reload Time: 4.0sec  \n!        Range: 72.0m  \n!     Accuracy: B         \n\nThis special shotgun scatters shots over a horizontal arc. The wide field of fire makes it extremely effective against multiple enemies. It is equally powerful against land and air enemies, but you must be careful not to catch your fellow soldiers in the line of fire.",
      "name": "WeaponText_Weapon026"
    },
    {"type": "string", "value": "Wideshot VR", "name": "WeaponName_Weapon027"},
    {
      "type": "string",
      "value": "!     Capacity: 8     \n! Rate of Fire: 1.0/sec\n!       Damage: 26.0×20\n!  Reload Time: 4.0sec  \n!        Range: 72.0m  \n!     Accuracy: B         \n\nAn upgraded Wideshot. Scatters rounds vertically, making it possible to attack enemies on land and in the air simultaneously. Firepower is also improved.",
      "name": "WeaponText_Weapon027"
    },
    {
      "type": "string",
      "value": "Sparrow Shot",
      "name": "WeaponName_Shotgun_SPS"
    },
    {
      "type": "string",
      "value": "!     Capacity: 10    \n! Rate of Fire: 4.0/sec\n!       Damage: 21.0×10\n!  Reload Time: 3.0sec  \n!        Range: 99.0m  \n!     Accuracy: B-        \n\nA high-performance shotgun with strong firepower and rapid-fire capability. This weapon launches countless rounds at once, making it easy to hit the target. Range, however, is not very long.",
      "name": "WeaponText_Shotgun_SPS"
    },
    {
      "type": "string",
      "value": "Buffalo G3 Burst",
      "name": "WeaponName_Weapon028"
    },
    {
      "type": "string",
      "value": "!     Capacity: 8     \n! Rate of Fire: 0.6×2/sec\n!       Damage: 40.0×15\n!  Reload Time: 4.0sec  \n!        Range: 150.0m \n!     Accuracy: B-        \n\nA double-barrel shotgun that releases 2 successive shots in a single attack. Rounds are concentrated to maximize firepower, enabling great damage in a small area. \n(This weapon has no auto-fire)",
      "name": "WeaponText_Weapon028"
    },
    {"type": "string", "value": "Buffalo G3", "name": "WeaponName_Weapon029"},
    {
      "type": "string",
      "value": "!     Capacity: 8     \n! Rate of Fire: 1.0/sec\n!       Damage: 40.0×15\n!  Reload Time: 4.0sec  \n!        Range: 150.0m \n!     Accuracy: B         \n\nA new Buffalo shotgun model. Shots are concentrated in a small area, making it possible to deal terrifying damage to a single target. This is a pump-action model, and therefore takes time to reload.",
      "name": "WeaponText_Weapon029"
    },
    {
      "type": "string",
      "value": "Sparrow Shot M2",
      "name": "WeaponName_Weapon030"
    },
    {
      "type": "string",
      "value": "!     Capacity: 10    \n! Rate of Fire: 5.0/sec\n!       Damage: 29.0×15\n!  Reload Time: 5.0sec  \n!        Range: 120.0m \n!     Accuracy: B-        \n\nA more powerful Sparrow Shot model with an even greater rate of fire. Firepower, number of shots fired, and range are all improved as well.\nGas-operated.",
      "name": "WeaponText_Weapon030"
    },
    {"type": "string", "value": "Governor 50", "name": "WeaponName_Weapon031"},
    {
      "type": "string",
      "value": "!     Capacity: 8     \n! Rate of Fire: 1.0/sec\n!       Damage: 40.0×50\n!  Reload Time: 4.0sec  \n!        Range: 150.0m \n!     Accuracy: D         \n\nA superb shotgun with tremendous firepower. This weapon features an incredibly wide shot pattern and high number of shots. It is far deadlier than the original model, and there are rumors that it was developed with Ravager technology...",
      "name": "WeaponText_Weapon031"
    },
    {"type": "string", "value": "Wideshot A1", "name": "WeaponName_Weapon032"},
    {
      "type": "string",
      "value": "!     Capacity: 10    \n! Rate of Fire: 1.1/sec\n!       Damage: 60.0×25\n!  Reload Time: 5.3sec  \n!        Range: 160.0m \n!     Accuracy: B         \n\nA powered-up Wideshot that spreads shots out over a wide horizontal field, making it possible to attack several enemies at once. It is extremely effective against both land and air enemies, but you must be careful not to catch other soldiers in the blast.",
      "name": "WeaponText_Weapon032"
    },
    {"type": "string", "value": "Buffalo G4", "name": "WeaponName_Weapon033"},
    {
      "type": "string",
      "value": "!     Capacity: 15    \n! Rate of Fire: 1.0/sec\n!       Damage: 90.0×15\n!  Reload Time: 8.0sec  \n!        Range: 154.0m \n!     Accuracy: B-        \n\nA new Buffalo shotgun. Power and capacity are improved, but this pump-action model still suffers from a slow reload time.",
      "name": "WeaponText_Weapon033"
    },
    {
      "type": "string",
      "value": "Wideshot A1-VR",
      "name": "WeaponName_Weapon034"
    },
    {
      "type": "string",
      "value": "!     Capacity: 10    \n! Rate of Fire: 1.0/sec\n!       Damage: 72.0×25\n!  Reload Time: 5.3sec  \n!        Range: 168.0m \n!     Accuracy: B         \n\nA powered-up Wideshot that disperses shots over a wide vertical field, making it possible to attack enemies on land and in the air simultaneously.",
      "name": "WeaponText_Weapon034"
    },
    {"type": "string", "value": "Buffalo G9", "name": "WeaponName_Weapon035"},
    {
      "type": "string",
      "value": "!     Capacity: 13    \n! Rate of Fire: 1.0/sec\n!       Damage: 110.0×15\n!  Reload Time: 8.0sec  \n!        Range: 176.0m \n!     Accuracy: B-        \n\nA new Buffalo shotgun with increased horizontal spread to make the weapon more versatile. Firepower is also improved, making it an extremely powerful weapon. It is, however, a pump-action model, and takes time to reload.",
      "name": "WeaponText_Weapon035"
    },
    {
      "type": "string",
      "value": "Sparrow Shot M3",
      "name": "WeaponName_Weapon036"
    },
    {
      "type": "string",
      "value": "!     Capacity: 15    \n! Rate of Fire: 6.0/sec\n!       Damage: 45.0×15\n!  Reload Time: 5.0sec  \n!        Range: 150.0m \n!     Accuracy: B-        \n\nA new Sparrow Shot model. This powerful gas-operated shotgun pushes rate of fire to the limit. Range is also greatly improved.",
      "name": "WeaponText_Weapon036"
    },
    {"type": "string", "value": "Governor 100", "name": "WeaponName_Weapon037"},
    {
      "type": "string",
      "value": "!     Capacity: 6     \n! Rate of Fire: 0.7/sec\n!       Damage: 60.0×100\n!  Reload Time: 4.0sec  \n!        Range: 170.0m \n!     Accuracy: D         \n\nThe final upgrade of the Governor shotgun. This terrifyingly powerful model fires 100 shots dispersed over a wide shot pattern.",
      "name": "WeaponText_Weapon037"
    },
    {"type": "string", "value": "Buffalo GSS", "name": "WeaponName_Weapon038"},
    {
      "type": "string",
      "value": "!     Capacity: 15    \n! Rate of Fire: 1.0/sec\n!       Damage: 170.0×15\n!  Reload Time: 8.0sec  \n!        Range: 221.0m \n!     Accuracy: B-        \n\nThe ultimate Buffalo shotgun. Power has been remarkably improved without compromising overall balance. This is, however, a pump-action model, and takes time to reload.",
      "name": "WeaponText_Weapon038"
    },
    {
      "type": "string",
      "value": "Sparrow Shot MX",
      "name": "WeaponName_Weapon039"
    },
    {
      "type": "string",
      "value": "!     Capacity: 16    \n! Rate of Fire: 4.0/sec\n!       Damage: 80.0×15\n!  Reload Time: 4.0sec  \n!        Range: 184.0m \n!     Accuracy: B-        \n\nThe final Sparrow Shot model. Rate of fire has been slightly compromised, but firepower and range have been dramatically improved. A fearsome weapon overall.",
      "name": "WeaponText_Weapon039"
    },
    {"type": "string", "value": "Buffalo Wide", "name": "WeaponName_Weapon040"},
    {
      "type": "string",
      "value": "!     Capacity: 15    \n! Rate of Fire: 1.0/sec\n!       Damage: 220.0×15\n!  Reload Time: 6.7sec  \n!        Range: 221.0m \n!     Accuracy: B-        \n\nThis ultimate shotgun combines the Buffalo's firepower with the Wideshot's shot pattern. It is based on the Buffalo GSS, but has a wider horizontal field of fire, as well as improved firepower and reduced reload time.",
      "name": "WeaponText_Weapon040"
    },
    {
      "type": "string",
      "value": "MMF40",
      "name": "WeaponName_SniperRifle_SNR227"
    },
    {
      "type": "string",
      "value": "!     Capacity: 5          Zoom: 4.0x  \n! Rate of Fire: 0.7/sec\n!       Damage: 110.0   \n!  Reload Time: 2.0sec  \n!        Range: 600.0m \n!     Accuracy: S+        \n\nA high caliber anti-material sniper rifle powerful enough to penetrate armored vehicles. The attached 4x zoom scope makes it possible to snipe enemies from afar.",
      "name": "WeaponText_SniperRifle_SNR227"
    },
    {"type": "string", "value": "MMF40-RA", "name": "WeaponName_Weapon041"},
    {
      "type": "string",
      "value": "!     Capacity: 5          Zoom: 4.0x  \n! Rate of Fire: 2.0/sec\n!       Damage: 65.0    \n!  Reload Time: 2.0sec  \n!        Range: 600.0m \n!     Accuracy: S+        \n\nThis RA model MMF40 emphasizes rapid fire, making it effective even in close range combat. Individual shot power is decreased, but its new rapid-fire capability allows it to deal greater damage overall. This is an excellent weapon at close or long range.",
      "name": "WeaponText_Weapon041"
    },
    {"type": "string", "value": "Stringer", "name": "WeaponName_Weapon042"},
    {
      "type": "string",
      "value": "!     Capacity: 1          Zoom: 8.0x  \n! Rate of Fire: ----   \n!       Damage: 500.0   \n!  Reload Time: 5.0sec  \n!        Range: 800.0m \n!     Accuracy: S+        \n\nA powerful rifle that can fire bullets through multiple targets in the line of fire. Range and accuracy are both high, but due to the special construction required for its armor-piercing capability, shots must be loaded individually. An 8x zoom scope is attached.",
      "name": "WeaponText_Weapon042"
    },
    {"type": "string", "value": "MMF41", "name": "WeaponName_Weapon043"},
    {
      "type": "string",
      "value": "!     Capacity: 7          Zoom: 6.0x  \n! Rate of Fire: 0.7/sec\n!       Damage: 200.0   \n!  Reload Time: 2.0sec  \n!        Range: 600.0m \n!     Accuracy: A-        \n\nA new model MMF sniper rifle. This weapon boasts improved overall performance and is equipped with a 6x zoom scope. The drawback is a slight decrease in accuracy.",
      "name": "WeaponText_Weapon043"
    },
    {"type": "string", "value": "MMF41-B3", "name": "WeaponName_Weapon044"},
    {
      "type": "string",
      "value": "!     Capacity: 7          Zoom: 4.0x  \n! Rate of Fire: 0.7×3/sec\n!       Damage: 110.0   \n!  Reload Time: 2.0sec  \n!        Range: 720.0m \n!     Accuracy: S+        \n\nA custom MM41 that fires 3-shot bursts. Firing once will release 3 bullets in rapid succession. This, however, depends on the number bullets in the chamber.\n(There is no full-auto function, so you need to release the Attack button once to fire again.)",
      "name": "WeaponText_Weapon044"
    },
    {
      "type": "string",
      "value": "Lysander",
      "name": "WeaponName_SniperRifle_RTH"
    },
    {
      "type": "string",
      "value": "!     Capacity: 7          Zoom: 8.0x  \n! Rate of Fire: 0.3/sec\n!       Damage: 550.0   \n!  Reload Time: 4.0sec  \n!        Range: 720.0m \n!     Accuracy: S+        \n\nA high caliber sniper rifle. This weapon is considerably more powerful than the MMF40 series. However, the complex loading mechanism required for its large rounds renders this rifle incapable of rapid-fire.",
      "name": "WeaponText_SniperRifle_RTH"
    },
    {"type": "string", "value": "MMF42", "name": "WeaponName_Weapon045"},
    {
      "type": "string",
      "value": "!     Capacity: 5          Zoom: 4.0x  \n! Rate of Fire: 0.7/sec\n!       Damage: 270.0   \n!  Reload Time: 2.0sec  \n!        Range: 600.0m \n!     Accuracy: S+        \n\nA new MMF model sniper rifle that improves on the MMF41's poor accuracy. Also notable is its high bullet velocity.",
      "name": "WeaponText_Weapon045"
    },
    {"type": "string", "value": "MMF42-RA", "name": "WeaponName_Weapon046"},
    {
      "type": "string",
      "value": "!     Capacity: 20         Zoom: 6.0x  \n! Rate of Fire: 10.0/sec\n!       Damage: 50.0    \n!  Reload Time: 2.0sec  \n!        Range: 400.0m \n!     Accuracy: S+        \n\nAn upgraded MMF42. This RA model is capable of rapid-fire, making it effective in close combat as well. Range is somewhat decreased.",
      "name": "WeaponText_Weapon046"
    },
    {
      "type": "string",
      "value": "Zero Laser Rifle",
      "name": "WeaponName_BonusWeapon01"
    },
    {
      "type": "string",
      "value": "!     Capacity: 180        Zoom: 4.0x  \n! Rate of Fire: 60.0/sec\n!       Damage: 100.0   \n!  Reload Time: ----    \n!        Range: 600.0m \n!     Accuracy: S+        \n\nA high-energy laser gun developed with Ravager technology. It is incredibly powerful, but requires heavy equipment to recharge, making it impossible to reload on the battlefield.",
      "name": "WeaponText_BonusWeapon01"
    },
    {"type": "string", "value": "MMF43", "name": "WeaponName_Weapon047"},
    {
      "type": "string",
      "value": "!     Capacity: 8          Zoom: 4.0x  \n! Rate of Fire: 0.7/sec\n!       Damage: 440.0   \n!  Reload Time: 3.3sec  \n!        Range: 600.0m \n!     Accuracy: S+        \n\nAn upgraded MMF sniper rifle with vastly improved overall performance.",
      "name": "WeaponText_Weapon047"
    },
    {"type": "string", "value": "MMF43-B2", "name": "WeaponName_Weapon048"},
    {
      "type": "string",
      "value": "!     Capacity: 10         Zoom: 4.0x  \n! Rate of Fire: 0.7×2/sec\n!       Damage: 300.0   \n!  Reload Time: 3.3sec  \n!        Range: 500.0m \n!     Accuracy: S+        \n\nA customized MMF43. This model fires 2 shots in rapid succession. The draw-back is its inferior range.\n(This weapon has no auto-fire)",
      "name": "WeaponText_Weapon048"
    },
    {"type": "string", "value": "Stringer J2", "name": "WeaponName_Weapon049"},
    {
      "type": "string",
      "value": "!     Capacity: 1          Zoom: 4.0x  \n! Rate of Fire: ----   \n!       Damage: 2000.0  \n!  Reload Time: 3.5sec  \n!        Range: 800.0m \n!     Accuracy: S+        \n\nA fearsomely powerful Stringer model with armor-piercing rounds. This weapon fires through multiple targets, dealing damage to anything in the line of fire. Bullets, however, must be individually loaded due to the special construction required for its armor-piercing capability. It is equipped with a 4x zoom scope.",
      "name": "WeaponText_Weapon049"
    },
    {"type": "string", "value": "MMF50", "name": "WeaponName_Weapon050"},
    {
      "type": "string",
      "value": "!     Capacity: 20         Zoom: 12.0x \n! Rate of Fire: 1.0/sec\n!       Damage: 660.0   \n!  Reload Time: 5.0sec  \n!        Range: 810.0m \n!     Accuracy: B         \n\nA new MMF model with improved power and ammo capacity. While equipped with a high-performance 12x zoom scope, the weapon is, fatally, highly inaccurate. It is up to the user's skill whether this weapon can be put to good use or not.",
      "name": "WeaponText_Weapon050"
    },
    {"type": "string", "value": "Five Card XA", "name": "WeaponName_Weapon051"},
    {
      "type": "string",
      "value": "!     Capacity: 8          Zoom: 4.0x  \n! Rate of Fire: 0.7/sec\n!       Damage: 120.0×5\n!  Reload Time: 3.0sec  \n!        Range: 500.0m \n!     Accuracy: A+        \n\nA high-performance sniper rifle that fires 5 shots at once. This model boasts high firepower, but range is relatively short.",
      "name": "WeaponText_Weapon051"
    },
    {"type": "string", "value": "Lysander 2", "name": "WeaponName_Weapon052"},
    {
      "type": "string",
      "value": "!     Capacity: 7          Zoom: 8.0x  \n! Rate of Fire: 0.3/sec\n!       Damage: 2700.0  \n!  Reload Time: 4.0sec  \n!        Range: 1000.0m\n!     Accuracy: S+        \n\nA high caliber sniper rifle with greater firepower than a tank turret. It is, however, impossible to fire rapidly, since each bullet must be loaded into the chamber individually.",
      "name": "WeaponText_Weapon052"
    },
    {"type": "string", "value": "MMF100", "name": "WeaponName_Weapon053"},
    {
      "type": "string",
      "value": "!     Capacity: 10         Zoom: 4.0x  \n! Rate of Fire: 1.1/sec\n!       Damage: 820.0   \n!  Reload Time: 3.3sec  \n!        Range: 600.0m \n!     Accuracy: S+        \n\nA new MMF model sniper rifle. It has an improved rate of fire and is now very easy to use. Range is not very long, but it has good overall performance.",
      "name": "WeaponText_Weapon053"
    },
    {"type": "string", "value": "Five Card XB", "name": "WeaponName_Weapon054"},
    {
      "type": "string",
      "value": "!     Capacity: 8          Zoom: 6.0x  \n! Rate of Fire: 0.7/sec\n!       Damage: 240.0×5\n!  Reload Time: 3.0sec  \n!        Range: 2000.0m\n!     Accuracy: A+        \n\nA powered-up Five Card XA that fires 5 rounds at once. Firepower has been increased, with range also improved. It fires special bullets that ricochet off of walls, making it possible to snipe enemies hidden behind obstacles.",
      "name": "WeaponText_Weapon054"
    },
    {"type": "string", "value": "MMF200", "name": "WeaponName_Weapon055"},
    {
      "type": "string",
      "value": "!     Capacity: 11         Zoom: 4.0x  \n! Rate of Fire: 1.0/sec\n!       Damage: 990.0   \n!  Reload Time: 3.3sec  \n!        Range: 770.0m \n!     Accuracy: S+        \n\nThe final MMF sniper rifle model. Overall performance has been improved, and an extremely high bullet velocity enables accurate shots.",
      "name": "WeaponText_Weapon055"
    },
    {"type": "string", "value": "Lysander F", "name": "WeaponName_Weapon056"},
    {
      "type": "string",
      "value": "!     Capacity: 7          Zoom: 10.0x \n! Rate of Fire: 0.3/sec\n!       Damage: 3800.0  \n!  Reload Time: 4.0sec  \n!        Range: 975.0m \n!     Accuracy: S+        \n\nAn upgraded Lysander 2. This model was developed with Ravager technology, and is the most powerful sniper rifle available. Its terrifying firepower makes up for a low rate of fire.",
      "name": "WeaponText_Weapon056"
    },
    {"type": "string", "value": "Lysander Z", "name": "WeaponName_Weapon057"},
    {
      "type": "string",
      "value": "!     Capacity: 8          Zoom: 10.0x \n! Rate of Fire: 0.3/sec\n!       Damage: 5500.0  \n!  Reload Time: 4.0sec  \n!        Range: 975.0m \n!     Accuracy: S+        \n\nThe final Lysander model. With its incredible firepower, this weapon proves to be the ultimate sniper rifle.",
      "name": "WeaponText_Weapon057"
    },
    {
      "type": "string",
      "value": "Stingray M1",
      "name": "WeaponName_RocketLauncher01"
    },
    {
      "type": "string",
      "value": "!     Capacity: 2          Range: 3000.0m\n! Rate of Fire: 1.0/sec\n!       Damage: 100.0   \n!  Reload Time: 1.8sec  \n!   Blast Area: 5.0m       \n!     Accuracy: A+        \n\nA piece of personal artillery that fires rockets that explode on impact, dealing damage over a wide area. Developed in 2008, this new model features considerably longer range than the original. \n(Take caution to avoid being caught in the blast.)",
      "name": "WeaponText_RocketLauncher01"
    },
    {"type": "string", "value": "Stingray ST", "name": "WeaponName_Weapon058"},
    {
      "type": "string",
      "value": "!     Capacity: 2          Range: 3000.0m\n! Rate of Fire: 1.0/sec\n!       Damage: 130.0   \n!  Reload Time: 1.8sec  \n!   Blast Area: 7.0m       \n!     Accuracy: A+        \n\nThis upgraded Stingray features greater power and a larger blast area, making it an even more powerful weapon.\nThis model has one of the longest ranges of any weapon.",
      "name": "WeaponText_Weapon058"
    },
    {"type": "string", "value": "Volcano 3A", "name": "WeaponName_Weapon059"},
    {
      "type": "string",
      "value": "!     Capacity: 2          Range: 3000.0m\n! Rate of Fire: 1.0/sec\n!       Damage: 100.0×3\n!  Reload Time: 1.5sec  \n!   Blast Area: 6.0m       \n!     Accuracy: B         \n\nA triple-barreled rocket launcher that fires 3 small rockets simultaneously.",
      "name": "WeaponText_Weapon059"
    },
    {
      "type": "string",
      "value": "Stingray ST2",
      "name": "WeaponName_RocketLauncherGDD"
    },
    {
      "type": "string",
      "value": "!     Capacity: 2          Range: 3000.0m\n! Rate of Fire: 1.0/sec\n!       Damage: 180.0   \n!  Reload Time: 1.5sec  \n!   Blast Area: 10.0m      \n!     Accuracy: A+        \n\nThis upgraded Stingray boasts significantly greater power and a larger blast area. Considered one of the best rocket launchers available, this weapon can damage several enemies with a single attack.\n(Take caution to avoid being caught in the blast.)",
      "name": "WeaponText_RocketLauncherGDD"
    },
    {
      "type": "string",
      "value": "Volcano 3W-Burst",
      "name": "WeaponName_Weapon060"
    },
    {
      "type": "string",
      "value": "!     Capacity: 4          Range: 3000.0m\n! Rate of Fire: 1.0×4/sec\n!       Damage: 65.0×3 \n!  Reload Time: 1.5sec  \n!   Blast Area: 6.0m       \n!     Accuracy: A+        \n\nA triple-barreled rocket launcher that fires 3 small rockets at once. A single attack with this fearsome weapon assaults enemies with 4 successive shots, for a total of 12 rockets. The shots scatter horizontally, making it extremely effective against large groups.",
      "name": "WeaponText_Weapon060"
    },
    {"type": "string", "value": "Cascade 1", "name": "WeaponName_Weapon061"},
    {
      "type": "string",
      "value": "!     Capacity: 20         Range: 3000.0m\n! Rate of Fire: 6.0/sec\n!       Damage: 120.0   \n!  Reload Time: 5.0sec  \n!   Blast Area: 2.0m       \n!     Accuracy: B-        \n\nA new rapid-firing rocket launcher. This weapon can deal massive damage to an enemy with successive shots. The downside is its low accuracy and small blast area.",
      "name": "WeaponText_Weapon061"
    },
    {
      "type": "string",
      "value": "A1 Plasma Launcher",
      "name": "WeaponName_Weapon062"
    },
    {
      "type": "string",
      "value": "!     Capacity: 4          Range: 300.0m \n! Rate of Fire: 2.0/sec\n!       Damage: 200.0   \n!  Reload Time: ----    \n!   Blast Area: 40.0m      \n!     Accuracy: S+        \n\nCreated with Ravager technology, this launcher sends all enemies in the area flying. Much concerning this technology has yet to be understood, and, currently, the plasma can only be replenished with special equipment. This makes it impossible to reload on the battlefield.",
      "name": "WeaponText_Weapon062"
    },
    {"type": "string", "value": "Goliath D1", "name": "WeaponName_Weapon063"},
    {
      "type": "string",
      "value": "!     Capacity: 1          Range: 3000.0m\n! Rate of Fire: ----        Zoom: 3.0x  \n!       Damage: 600.0   \n!  Reload Time: 3.0sec  \n!   Blast Area: 12.0m      \n!     Accuracy: A+        \n\nThis rocket launcher boasts the ultimate in firepower and a huge blast area.\nA 3x zoom scope is attached, giving it the accuracy to make it a solid long range weapon.",
      "name": "WeaponText_Weapon063"
    },
    {"type": "string", "value": "Stingray M2", "name": "WeaponName_Weapon064"},
    {
      "type": "string",
      "value": "!     Capacity: 3          Range: 3000.0m\n! Rate of Fire: 1.0/sec\n!       Damage: 230.0   \n!  Reload Time: 1.5sec  \n!   Blast Area: 8.0m       \n!     Accuracy: A+        \n\nThis update of the Stingray M1 has a smaller blast area than the Stingray ST2, but is more powerful and has a higher ammo capacity. The smaller blast reduces personal risk, making it more user-friendly.",
      "name": "WeaponText_Weapon064"
    },
    {"type": "string", "value": "Stingray M3", "name": "WeaponName_Weapon065"},
    {
      "type": "string",
      "value": "!     Capacity: 5          Range: 3000.0m\n! Rate of Fire: 1.0/sec\n!       Damage: 280.0   \n!  Reload Time: 1.5sec  \n!   Blast Area: 9.0m       \n!     Accuracy: A+        \n\nThe latest Stingray model. Even more powerful than the Stingray M2, this weapon achieves great overall balance. It has a high ammo capacity, and is easy to use.",
      "name": "WeaponText_Weapon065"
    },
    {
      "type": "string",
      "value": "A2 Plasma Launcher",
      "name": "WeaponName_Weapon066"
    },
    {
      "type": "string",
      "value": "!     Capacity: 20         Range: 600.0m \n! Rate of Fire: 1.5/sec\n!       Damage: 150.0×10\n!  Reload Time: ----    \n!   Blast Area: 6.0m       \n!     Accuracy: C         \n\nA proximity weapon made with Ravager technology. Fires a hail of plasma rounds. Special equipment is required to replenish plasma energy, making it impossible to reload on the battle field. Development of a portable plasma charger is currently underway.",
      "name": "WeaponText_Weapon066"
    },
    {"type": "string", "value": "Cascade 2", "name": "WeaponName_Weapon067"},
    {
      "type": "string",
      "value": "!     Capacity: 10         Range: 3000.0m\n! Rate of Fire: 6.0/sec\n!       Damage: 200.0   \n!  Reload Time: 1.5sec  \n!   Blast Area: 6.0m       \n!     Accuracy: A         \n\nA new Cascade rocket launcher that emphasizes firing speed. It is considerably faster and more powerful than the Cascade 1, and has a wider blast area as well. Reload time has been considerably shortened by reducing ammo capacity.",
      "name": "WeaponText_Weapon067"
    },
    {"type": "string", "value": "Goliath D2", "name": "WeaponName_Weapon068"},
    {
      "type": "string",
      "value": "!     Capacity: 1          Range: 3000.0m\n! Rate of Fire: ----        Zoom: 7.0x  \n!       Damage: 1200.0  \n!  Reload Time: 4.0sec  \n!   Blast Area: 15.0m      \n!     Accuracy: A+        \n\nAn upgraded version of the powerful Goliath rocket launcher. Both firepower and blast area are greatly improved. A scope for long distance firing is attached.",
      "name": "WeaponText_Weapon068"
    },
    {"type": "string", "value": "Stingray M4", "name": "WeaponName_Weapon069"},
    {
      "type": "string",
      "value": "!     Capacity: 4          Range: 3000.0m\n! Rate of Fire: 1.0/sec\n!       Damage: 500.0   \n!  Reload Time: 1.5sec  \n!   Blast Area: 10.0m      \n!     Accuracy: A+        \n\nA new version of the extremely well-balanced Stingray rocket launcher. This model features improved firepower and a larger blast width. Ammo capacity is somewhat reduced in exchange.",
      "name": "WeaponText_Weapon069"
    },
    {"type": "string", "value": "Volcano B10", "name": "WeaponName_Weapon070"},
    {
      "type": "string",
      "value": "!     Capacity: 10         Range: 3000.0m\n! Rate of Fire: 1.0×10/sec\n!       Damage: 400.0   \n!  Reload Time: 3.0sec  \n!   Blast Area: 10.0m      \n!     Accuracy: A+        \n\nAn upgraded Volcano rocket launcher model. Firing this weapon once releases a hail of 10 successive shots.",
      "name": "WeaponText_Weapon070"
    },
    {"type": "string", "value": "Goliath Z", "name": "WeaponName_Weapon071"},
    {
      "type": "string",
      "value": "!     Capacity: 1          Range: 3000.0m\n! Rate of Fire: ----        Zoom: 7.0x  \n!       Damage: 2500.0  \n!  Reload Time: 4.0sec  \n!   Blast Area: 20.0m      \n!     Accuracy: A+        \n\nThe final Goliath rocket launcher. This model has greater firepower and a larger blast area than any other weapon. It is also equipped with a scope, making it possible to aim carefully at long distance.\n(Due to the large blast area, it is dangerous to use at close range.)",
      "name": "WeaponText_Weapon071"
    },
    {"type": "string", "value": "Volcano 6W", "name": "WeaponName_Weapon072"},
    {
      "type": "string",
      "value": "!     Capacity: 2          Range: 3000.0m\n! Rate of Fire: 1.0/sec\n!       Damage: 300.0×6\n!  Reload Time: 3.0sec  \n!   Blast Area: 10.0m      \n!     Accuracy: S+        \n\nA 6-barreled rocket launcher. Fires 6 small rockets at once.",
      "name": "WeaponText_Weapon072"
    },
    {
      "type": "string",
      "value": "A3 Plasma Launcher",
      "name": "WeaponName_Weapon073"
    },
    {
      "type": "string",
      "value": "!     Capacity: 20         Range: 200.0m\n! Rate of Fire: 2.0/sec\n!       Damage: 1000.0  \n!  Reload Time: ----    \n!   Blast Area: 30.0m      \n!     Accuracy: S+        \n\nDeveloped with Ravager technology, this proximity weapon fires explosive balls of plasma. The shots fall to the ground, and are dangerous if not fired upwards. Special equipment is needed to replenish plasma energy, making it impossible to reload on the battle field.",
      "name": "WeaponText_Weapon073"
    },
    {"type": "string", "value": "Stingray M99", "name": "WeaponName_Weapon074"},
    {
      "type": "string",
      "value": "!     Capacity: 5          Range: 3000.0m\n! Rate of Fire: 1.0/sec\n!       Damage: 1200.0  \n!  Reload Time: 2.0sec  \n!   Blast Area: 15.0m      \n!     Accuracy: A+        \n\nThe final Stingray model. This ultimate rocket launcher boasts terrifying firepower and a large blast area. It is said to have been made with Ravager technology, but the truth is unknown.",
      "name": "WeaponText_Weapon074"
    },
    {"type": "string", "value": "Stingray MF", "name": "WeaponName_Weapon075"},
    {
      "type": "string",
      "value": "!     Capacity: 5          Range: 3000.0m\n! Rate of Fire: 1.0/sec     Zoom: 4.0x  \n!       Damage: 1500.0  \n!  Reload Time: 2.0sec  \n!   Blast Area: 15.0m      \n!     Accuracy: A+        \n\nOne of the most powerful rocket launchers. Based on the Stingray M99, this version pushes firepower to the limit. Rockets now travel faster, making it possible to aim and fire at fast moving targets. This versatile weapon is also equipped with a scope for long distance firing.",
      "name": "WeaponText_Weapon075"
    },
    {
      "type": "string",
      "value": "Genocide Gun",
      "name": "WeaponName_BonusWeapon05"
    },
    {
      "type": "string",
      "value": "!     Capacity: 1          Range: 6000.0m\n! Rate of Fire: ----        Zoom: 6.0x  \n!       Damage: 1000000.0\n!  Reload Time: 3.3sec  \n!   Blast Area: 75.0m      \n!     Accuracy: S+        \n\nAn ultimate weapon created with Ravager technology. Possesses terrifying firepower and a devastatingly large blast width.",
      "name": "WeaponText_BonusWeapon05"
    },
    {
      "type": "string",
      "value": "Air Tortoise 01",
      "name": "WeaponName_Missile_SkyTT"
    },
    {
      "type": "string",
      "value": "!     Capacity: 1           Homing: S\n! Rate of Fire: ----   \n!       Damage: 400.0   \n!  Reload Time: 10.0sec \n!   Blast Area: 10.0m      \n\nA large guided missile that emphasizes firepower. This missile is extremely slow, but homes in well, slowly stalking its target. This model is a prototype, and therefore is lacking in firepower.",
      "name": "WeaponText_Missile_SkyTT"
    },
    {
      "type": "string",
      "value": "ME1 Emerald",
      "name": "WeaponName_Missile_EM0"
    },
    {
      "type": "string",
      "value": "!     Capacity: 2           Homing: C\n! Rate of Fire: 1.0/sec\n!       Damage: 150.0   \n!  Reload Time: 1.5sec  \n!   Blast Area: 5.0m       \n\nA new personal missile launcher model that was just officially brought into use in 2010. Fires guided missiles. Since it is a prototype, Homing is low, and it often misses its mark.",
      "name": "WeaponText_Missile_EM0"
    },
    {"type": "string", "value": "MLRA", "name": "WeaponName_Weapon076"},
    {
      "type": "string",
      "value": "!     Capacity: 10          Homing: B\n! Rate of Fire: 6.0/sec\n!       Damage: 32.0    \n!  Reload Time: 3.0sec  \n!   Blast Area: 1.0m       \n\nA missile launcher with a rapid rate of fire. Fires small guided missiles that home in on the enemy 0.5 seconds after being launched.",
      "name": "WeaponText_Weapon076"
    },
    {
      "type": "string",
      "value": "Air Tortoise 02",
      "name": "WeaponName_Weapon077"
    },
    {
      "type": "string",
      "value": "!     Capacity: 1           Homing: S\n! Rate of Fire: ----   \n!       Damage: 800.0   \n!  Reload Time: 10.0sec \n!   Blast Area: 20.0m      \n\nThe second version of the Air Tortoise. Firepower is increased tremendously, making it effective in actual combat. The resulting explosion measures 40 meters in diameter.",
      "name": "WeaponText_Weapon077"
    },
    {"type": "string", "value": "ME2 Emerald", "name": "WeaponName_Weapon078"},
    {
      "type": "string",
      "value": "!     Capacity: 2           Homing: B-\n! Rate of Fire: 1.0/sec\n!       Damage: 150.0   \n!  Reload Time: 1.5sec  \n!   Blast Area: 5.0m       \n\nA battle ready version of the Emerald personal guided missile launcher. A vastly improved guidance system makes this an excellent weapon.",
      "name": "WeaponText_Weapon078"
    },
    {"type": "string", "value": "MLRA-2", "name": "WeaponName_Weapon079"},
    {
      "type": "string",
      "value": "!     Capacity: 10          Homing: B+\n! Rate of Fire: 6.0/sec\n!       Damage: 32.0    \n!  Reload Time: 3.0sec  \n!   Blast Area: 1.0m       \n\nAn upgraded MLRA missile launcher with improved Homing. Missiles are constantly guided towards the enemy, making this model an extremely powerful weapon.",
      "name": "WeaponText_Weapon079"
    },
    {"type": "string", "value": "ME3 Emerald", "name": "WeaponName_Weapon080"},
    {
      "type": "string",
      "value": "!     Capacity: 2           Homing: B\n! Rate of Fire: 1.0/sec\n!       Damage: 200.0   \n!  Reload Time: 1.5sec  \n!   Blast Area: 5.0m       \n\nA powered-up Emerald personal missile launcher. Improved firepower makes this an even better weapon.",
      "name": "WeaponText_Weapon080"
    },
    {"type": "string", "value": "MLRA-3", "name": "WeaponName_Weapon081"},
    {
      "type": "string",
      "value": "!     Capacity: 30          Homing: A-\n! Rate of Fire: 10.0/sec\n!       Damage: 50.0    \n!  Reload Time: 5.0sec  \n!   Blast Area: 1.0m       \n\nAn upgraded MLRA model with better firepower and an improved guidance system. Ammo capacity is also increased. Fires successive small missiles with high Homing. The blast area produced by each shot is not very big.",
      "name": "WeaponText_Weapon081"
    },
    {
      "type": "string",
      "value": "Prominence M1",
      "name": "WeaponName_Weapon082"
    },
    {
      "type": "string",
      "value": "!     Capacity: 1           Homing: C+\n! Rate of Fire: ----          Zoom: 6.0x  \n!       Damage: 1500.0  \n!  Reload Time: 5.0sec  \n!   Blast Area: 15.0m      \n\nFires large missiles that fly straight for 5 seconds after being fired, before homing in on the target. Can reach long distance targets or those hidden behind obstacles by aiming upwards. Equipped with a scope to confirm point of impact.",
      "name": "WeaponText_Weapon082"
    },
    {"type": "string", "value": "FORK-A20", "name": "WeaponName_Weapon083"},
    {
      "type": "string",
      "value": "!     Capacity: 1           Homing: A+\n! Rate of Fire: ----   \n!       Damage: 50.0×20\n!  Reload Time: 3.0sec  \n!   Blast Area: 1.0m       \n\nA missile launcher that fires 20 small high-speed missiles at once.",
      "name": "WeaponText_Weapon083"
    },
    {"type": "string", "value": "MLRA-TW", "name": "WeaponName_Weapon084"},
    {
      "type": "string",
      "value": "!     Capacity: 20          Homing: B-\n! Rate of Fire: 10.0/sec\n!       Damage: 100.0×2\n!  Reload Time: 5.0sec  \n!   Blast Area: 1.0m       \n\nA powered-up MLRA model. This is a double-barreled version that fires 2 small guided missiles at once. Each missile now has greater firepower. Shots are fired to the left and right before chasing the enemy.",
      "name": "WeaponText_Weapon084"
    },
    {"type": "string", "value": "MEX Emerald", "name": "WeaponName_Weapon085"},
    {
      "type": "string",
      "value": "!     Capacity: 4           Homing: A+\n! Rate of Fire: 1.0/sec\n!       Damage: 400.0   \n!  Reload Time: 1.5sec  \n!   Blast Area: 7.0m       \n\nAn improved version of the Emerald personal missile launcher. Overall performance is improved, making it better suited for combat.",
      "name": "WeaponText_Weapon085"
    },
    {
      "type": "string",
      "value": "Air Tortoise ME",
      "name": "WeaponName_Weapon086"
    },
    {
      "type": "string",
      "value": "!     Capacity: 1           Homing: S\n! Rate of Fire: ----   \n!       Damage: 4000.0  \n!  Reload Time: 10.0sec \n!   Blast Area: 30.0m      \n\nA battle-ready Air Tortoise missile. Boasts even greater firepower than the prototype model and causes an explosion 60 meters in diameter. Missile speed is still characteristically slow.",
      "name": "WeaponText_Weapon086"
    },
    {
      "type": "string",
      "value": "Prominence M2",
      "name": "WeaponName_Weapon087"
    },
    {
      "type": "string",
      "value": "!     Capacity: 1           Homing: C+   \n! Rate of Fire: ----          Zoom: 6.0x  \n!       Damage: 4000.0  \n!  Reload Time: 5.0sec  \n!   Blast Area: 20.0m      \n\nA missile with strong Homing and impressive firepower. Missiles fly straight for 5 seconds, after which they begin to home in. Can reach long distance targets or those hidden behind obstacles by aiming upwards. Equipped with a scope to confirm point of impact.",
      "name": "WeaponText_Weapon087"
    },
    {"type": "string", "value": "FORK-X20", "name": "WeaponName_Weapon088"},
    {
      "type": "string",
      "value": "!     Capacity: 1           Homing: A+\n! Rate of Fire: ----   \n!       Damage: 90.0×20\n!  Reload Time: 3.0sec  \n!   Blast Area: 2.0m       \n\nA powered-up Fork A20. This model fires 20 small high-speed missiles at once.",
      "name": "WeaponText_Weapon088"
    },
    {
      "type": "string",
      "value": "Prominence MA",
      "name": "WeaponName_Weapon089"
    },
    {
      "type": "string",
      "value": "!     Capacity: 1           Homing: C\n! Rate of Fire: ----          Zoom: 6.0x  \n!       Damage: 15000.0 \n!  Reload Time: 20.0sec \n!   Blast Area: 40.0m      \n\nThe final Prominence missile pushes size to the limit and boasts ridiculous firepower. Fired into the air, the missile reaches the stratosphere, from where it drops onto enemies. Weak guidance makes it possible to fire straight at enemies using a scope.",
      "name": "WeaponText_Weapon089"
    },
    {"type": "string", "value": "MG10", "name": "WeaponName_HandGrenade01"},
    {
      "type": "string",
      "value": "!      Damage: 200.0   \n!        Fuse: Impact\n! Fuse Length: ----\n!  Blast Area: 5.0m       \n\nA basic hand grenade. Press and hold the attack button to increase throwing distance, and release it to throw the grenade. (The grenade's path is indicated by a red line.)\nOnce thrown, the grenade explodes on impact.",
      "name": "WeaponText_HandGrenade01"
    },
    {"type": "string", "value": "MG10J", "name": "WeaponName_Weapon090"},
    {
      "type": "string",
      "value": "!      Damage: 600.0   \n!        Fuse: Time\n! Fuse Length: 10sec \n!  Blast Area: 5.0m       \n\nA timed (J type) hand grenade. Press and hold the attack button to increase throwing distance, and release it to throw the grenade. Explodes 10 seconds after attack button is pressed. This weapon can be bounced off of walls and other objects.",
      "name": "WeaponText_Weapon090"
    },
    {"type": "string", "value": "MG11", "name": "WeaponName_Weapon091"},
    {
      "type": "string",
      "value": "!      Damage: 300.0   \n!        Fuse: Impact\n! Fuse Length: ----\n!  Blast Area: 10.0m      \n\nA powered-up MG10 grenade. A larger blast width makes this an effective weapon.\n\nPress and hold the attack button to increase throwing distance, and release it to throw the grenade. (The grenade's path is indicated by a red line.)\nOnce thrown, the grenade explodes on impact.",
      "name": "WeaponText_Weapon091"
    },
    {"type": "string", "value": "MG12", "name": "WeaponName_Weapon092"},
    {
      "type": "string",
      "value": "!      Damage: 500.0   \n!        Fuse: Impact\n! Fuse Length: ----\n!  Blast Area: 10.0m      \n\nA powered-up MG11 grenade.\nGreater firepower makes this an excellent weapon.\n\nPress and hold the attack button to increase throwing distance, and release it to throw the grenade. \n(The grenade's path is indicated by a red line.)\nOnce thrown, the grenade explodes on impact.",
      "name": "WeaponText_Weapon092"
    },
    {"type": "string", "value": "MG13", "name": "WeaponName_Weapon093"},
    {
      "type": "string",
      "value": "!      Damage: 2500.0  \n!        Fuse: Impact\n! Fuse Length: ----\n!  Blast Area: 20.0m      \n\nA hand grenade with incredible firepower. The power packed into this weapon makes it very heavy and impossible to throw far. It was stored in a sealed crate labeled \"Danger\".",
      "name": "WeaponText_Weapon093"
    },
    {"type": "string", "value": "MG13J", "name": "WeaponName_Weapon094"},
    {
      "type": "string",
      "value": "!      Damage: 2500.0  \n!        Fuse: Time\n! Fuse Length: 30sec \n!  Blast Area: 20.0m      \n\nAn upgraded MG13 grenade. Weight remains unchanged, but it now features a timed detonator, giving the user time to escape before the blast.\n\nExplodes 30 seconds after pressing the Attack button.",
      "name": "WeaponText_Weapon094"
    },
    {"type": "string", "value": "MG14", "name": "WeaponName_Weapon095"},
    {
      "type": "string",
      "value": "!      Damage: 1400.0  \n!        Fuse: Impact\n! Fuse Length: ----\n!  Blast Area: 11.0m      \n\nAn upgraded MG12 hand grenade. Firepower is a step above the previous model. Once thrown, the grenade will explode on impact.",
      "name": "WeaponText_Weapon095"
    },
    {"type": "string", "value": "MG14J", "name": "WeaponName_Weapon096"},
    {
      "type": "string",
      "value": "!      Damage: 2000.0  \n!        Fuse: Time\n! Fuse Length: 5sec  \n!  Blast Area: 12.0m      \n\nAn upgraded MG10J time-detonated grenade. This weapon has enormous firepower, but the time delay is short.",
      "name": "WeaponText_Weapon096"
    },
    {"type": "string", "value": "MG20", "name": "WeaponName_Weapon097"},
    {
      "type": "string",
      "value": "!      Damage: 2500.0  \n!        Fuse: Impact\n! Fuse Length: ----\n!  Blast Area: 13.0m      \n\nA more powerful grenade. Once thrown, the grenade will explode on impact.",
      "name": "WeaponText_Weapon097"
    },
    {"type": "string", "value": "MG21J", "name": "WeaponName_Weapon098"},
    {
      "type": "string",
      "value": "!      Damage: 4000.0  \n!        Fuse: Time\n! Fuse Length: 10sec \n!  Blast Area: 17.0m      \n\nA strong grenade with high firepower. Explodes 10 seconds after pressing the attack button.",
      "name": "WeaponText_Weapon098"
    },
    {"type": "string", "value": "MG29SJ", "name": "WeaponName_Weapon099"},
    {
      "type": "string",
      "value": "!      Damage: 7000.0  \n!        Fuse: Time\n! Fuse Length: 10sec \n!           Blast Area: 20.0m      \n\nA grenade that bounces off of various terrain in unpredictable directions.",
      "name": "WeaponText_Weapon099"
    },
    {"type": "string", "value": "MG30", "name": "WeaponName_Weapon100"},
    {
      "type": "string",
      "value": "!      Damage: 3500.0  \n!        Fuse: Impact\n! Fuse Length: ----\n!  Blast Area: 25.0m      \n\nThe most powerful hand grenade.",
      "name": "WeaponText_Weapon100"
    },
    {
      "type": "string",
      "value": "UM1 Grenade Launcher",
      "name": "WeaponName_Weapon101"
    },
    {
      "type": "string",
      "value": "!     Capacity: 4          \n! Rate of Fire: 2.0/sec              Fuse: Impact\n!       Damage: 110.0         Fuse Length: ----\n!  Reload Time: 2.0sec         Blast Area: 7.0m       \n\nA personal grenade launcher. Fires high performance grenades that explode on impact. Since these shots travel along an arc, it is possible to attack enemies hidden in trenches or behind cover.",
      "name": "WeaponText_Weapon101"
    },
    {
      "type": "string",
      "value": "UM1-J Grenade Launcher",
      "name": "WeaponName_Weapon102"
    },
    {
      "type": "string",
      "value": "!     Capacity: 4          \n! Rate of Fire: 2.0/sec              Fuse: Time\n!       Damage: 180.0         Fuse Length: 4sec  \n!  Reload Time: 2.0sec         Blast Area: 11.0m      \n\nA personal grenade launcher. Fires grenades that explode after 4 seconds. Since these shots travel along an arc, it is possible to attack enemies hidden behind obstacles or in trenches.",
      "name": "WeaponText_Weapon102"
    },
    {"type": "string", "value": "Stampede M1", "name": "WeaponName_Weapon103"},
    {
      "type": "string",
      "value": "!     Capacity: 1          \n! Rate of Fire: ----                 Fuse: Impact\n!       Damage: 100.0×10      Fuse Length: ----\n!  Reload Time: 5.0sec         Blast Area: 5.0m       \n\nA multi-barreled grenade launcher for support fire. Fires several small grenades simultaneously. By aiming this weapon into the air, you can carpet bomb the enemy with grenades. Speed has been reduced to make shots arc more easily.",
      "name": "WeaponText_Weapon103"
    },
    {
      "type": "string",
      "value": "UM2 Grenade Launcher",
      "name": "WeaponName_Weapon104"
    },
    {
      "type": "string",
      "value": "!     Capacity: 4          \n! Rate of Fire: 2.0/sec              Fuse: Impact\n!       Damage: 200.0         Fuse Length: ----\n!  Reload Time: 2.0sec         Blast Area: 8.0m       \n\nA powered-up grenade launcher with improved firepower and a larger blast area.",
      "name": "WeaponText_Weapon104"
    },
    {
      "type": "string",
      "value": "UM2-J Grenade Launcher",
      "name": "WeaponName_Weapon105"
    },
    {
      "type": "string",
      "value": "!     Capacity: 4          \n! Rate of Fire: 2.0/sec              Fuse: Time\n!       Damage: 280.0         Fuse Length: 4sec  \n!  Reload Time: 2.0sec         Blast Area: 12.0m      \n\nAn upgrade of the UM1-J Grenade Launcher. Fires grenades that detonate after a set time.",
      "name": "WeaponText_Weapon105"
    },
    {
      "type": "string",
      "value": "UMRA Grenade Launcher",
      "name": "WeaponName_Weapon106"
    },
    {
      "type": "string",
      "value": "!     Capacity: 12         \n! Rate of Fire: 7.5/sec              Fuse: Impact\n!       Damage: 100.0         Fuse Length: ----\n!  Reload Time: 3.0sec         Blast Area: 5.0m       \n\nA new grenade launcher with an excellent rate of fire. Fires successive grenades with incredible speed.",
      "name": "WeaponText_Weapon106"
    },
    {
      "type": "string",
      "value": "UM3-J Grenade Launcher",
      "name": "WeaponName_Weapon107"
    },
    {
      "type": "string",
      "value": "!     Capacity: 4          \n! Rate of Fire: 2.0/sec              Fuse: Time\n!       Damage: 400.0         Fuse Length: 4sec  \n!  Reload Time: 2.7sec         Blast Area: 13.0m      \n\nAn upgraded time-detonated grenade launcher. This weapon boasts excellent firepower and a large blast area.",
      "name": "WeaponText_Weapon107"
    },
    {
      "type": "string",
      "value": "Splash Grenade",
      "name": "WeaponName_Weapon108"
    },
    {
      "type": "string",
      "value": "!     Capacity: 1          \n! Rate of Fire: ----                 Fuse: Time\n!       Damage: 200.0×20      Fuse Length: 10sec \n!  Reload Time: 6.0sec         Blast Area: 8.0m       \n\nA new grenade launcher created with extraterrestrial technology. Fires as many as 20 splash grenades at once. These grenades bounce around and explode after 10 seconds. Since they bounce in an unpredictable pattern, caution is advised.",
      "name": "WeaponText_Weapon108"
    },
    {
      "type": "string",
      "value": "Sticky Grenade Prototype",
      "name": "WeaponName_Weapon109"
    },
    {
      "type": "string",
      "value": "!     Capacity: 1          \n! Rate of Fire: ----                 Fuse: Time\n!       Damage: 150.0×20      Fuse Length: 4sec  \n!  Reload Time: 6.0sec         Blast Area: 8.0m       \n\nA prototype grenade launcher created using extraterrestrial technology. Fires as many as 20 sticky grenades at a time. These grenades stick to whatever they hit and detonate after 4 seconds.",
      "name": "WeaponText_Weapon109"
    },
    {
      "type": "string",
      "value": "UM4 Grenade Launcher",
      "name": "WeaponName_Weapon110"
    },
    {
      "type": "string",
      "value": "!     Capacity: 5          \n! Rate of Fire: 2.0/sec              Fuse: Impact\n!       Damage: 450.0         Fuse Length: ----\n!  Reload Time: 3.0sec         Blast Area: 9.0m       \n\nA new grenade launcher model. Firepower is a step above the previous model and blast area is large.\nShots fly unhindered towards the target, making it possible to fire accurately at distant targets with practice.",
      "name": "WeaponText_Weapon110"
    },
    {
      "type": "string",
      "value": "BRUTE-J Triple Grenade Launcher",
      "name": "WeaponName_Weapon111"
    },
    {
      "type": "string",
      "value": "!     Capacity: 2          \n! Rate of Fire: 2.0/sec              Fuse: Time\n!       Damage: 600.0×3       Fuse Length: 4sec  \n!  Reload Time: 2.7sec         Blast Area: 15.0m      \n\nA triple grenade launcher that fires time-detonated grenades in 3 directions simultaneously. The resulting blast area is immense, and can wipe out a large group of enemies.",
      "name": "WeaponText_Weapon111"
    },
    {
      "type": "string",
      "value": "Splash Grenade α",
      "name": "WeaponName_Weapon112"
    },
    {
      "type": "string",
      "value": "!     Capacity: 1          \n! Rate of Fire: ----                 Fuse: Time\n!       Damage: 1000.0×20     Fuse Length: 10sec \n!  Reload Time: 6.0sec         Blast Area: 10.0m      \n\nA special grenade launcher that fires as many as 20 splash grenades at once. These grenades bounce around and explode after 10 seconds. Since they bounce in an unpredictable pattern, caution is advised.",
      "name": "WeaponText_Weapon112"
    },
    {
      "type": "string",
      "value": "BRUTE Triple Grenade Launcher",
      "name": "WeaponName_Weapon113"
    },
    {
      "type": "string",
      "value": "!     Capacity: 2          \n! Rate of Fire: 2.0/sec              Fuse: Impact\n!       Damage: 600.0×3       Fuse Length: ----\n!  Reload Time: 4.0sec         Blast Area: 9.0m       \n\nAn upgraded BRUTE-J triple grenade launcher. Fires grenades in 3 directions simultaneously. These grenades now explode upon impact, making it easier to use in battle.",
      "name": "WeaponText_Weapon113"
    },
    {
      "type": "string",
      "value": "Sticky Grenade",
      "name": "WeaponName_Weapon114"
    },
    {
      "type": "string",
      "value": "!     Capacity: 1          \n! Rate of Fire: ----                 Fuse: Time\n!       Damage: 400.0×20      Fuse Length: 4sec  \n!  Reload Time: 6.0sec         Blast Area: 10.0m      \n\nA special grenade launcher that fires 20 sticky grenades simultaneously. These grenades stick to whatever they hit and explode after 4 seconds.",
      "name": "WeaponText_Weapon114"
    },
    {"type": "string", "value": "Stampede M2", "name": "WeaponName_Weapon115"},
    {
      "type": "string",
      "value": "!     Capacity: 1          \n! Rate of Fire: ----                 Fuse: Impact\n!       Damage: 400.0×25      Fuse Length: ----\n!  Reload Time: 6.0sec         Blast Area: 7.0m       \n\nA powered-up Stampede M1 grenade launcher. This fearsome weapon fires more shots than before, and can launch a rain of grenades to drop onto the enemy.",
      "name": "WeaponText_Weapon115"
    },
    {
      "type": "string",
      "value": "CRUMBLE Twin Grenade Launcher",
      "name": "WeaponName_Weapon116"
    },
    {
      "type": "string",
      "value": "!     Capacity: 2          \n! Rate of Fire: 1.0/sec              Fuse: Impact\n!       Damage: 1100.0×2      Fuse Length: ----\n!  Reload Time: 3.0sec         Blast Area: 16.0m      \n\nA twin grenade launcher with incredible firepower that fires grenades in two directions. The grenades detonate on impact, creating a huge explosion. Caution is advised at close range.",
      "name": "WeaponText_Weapon116"
    },
    {
      "type": "string",
      "value": "Sticky Grenade α",
      "name": "WeaponName_Weapon117"
    },
    {
      "type": "string",
      "value": "!     Capacity: 1          \n! Rate of Fire: ----                 Fuse: Time\n!       Damage: 5000.0        Fuse Length: 4sec  \n!  Reload Time: 3.0sec         Blast Area: 20.0m      \n\nAn upgraded sticky grenade launcher. Fires one sticky grenade at a time, but each one can cause immense destruction. These grenades explode 4 seconds after sticking to the target.",
      "name": "WeaponText_Weapon117"
    },
    {
      "type": "string",
      "value": "UMAX Grenade Launcher",
      "name": "WeaponName_Weapon118"
    },
    {
      "type": "string",
      "value": "!     Capacity: 4          \n! Rate of Fire: 1.0/sec              Fuse: Impact\n!       Damage: 2000.0        Fuse Length: ----\n!  Reload Time: 5.0sec         Blast Area: 20.0m      \n\nThe final UM grenade launcher. Firepower and blast area have been pushed to the limit in this ultimate model. It is a fearsome weapon that can destroy enemies with a tremendous explosion. Grenades detonate on impact.\n(Some pronounce the name as \"Oo-max\",but the official pronunciation is \"You-max.\")",
      "name": "WeaponText_Weapon118"
    },
    {"type": "string", "value": "Stampede XM", "name": "WeaponName_Weapon119"},
    {
      "type": "string",
      "value": "!     Capacity: 1          \n! Rate of Fire: ----                 Fuse: Impact\n!       Damage: 1000.0×30     Fuse Length: ----\n!  Reload Time: 6.0sec         Blast Area: 12.0m      \n\nAn upgraded Stampede M2 grenade launcher. Fires a greater number of shots and creates a larger explosion, making it a strong weapon capable of obliterating anything over a wide area.",
      "name": "WeaponText_Weapon119"
    },
    {
      "type": "string",
      "value": "Acid Shot Prototype",
      "name": "WeaponName_Weapon120"
    },
    {
      "type": "string",
      "value": "!     Capacity: 20    \n! Rate of Fire: 2.0/sec\n!       Damage: 10.0×6 \n!  Reload Time: 3.0sec  \n!        Range: 50.0m\n!     Accuracy: B-        \n\nA special gun that fires strong acid that can dissolve metal in an instant, this weapon is a successful application of the giant insects' bodily fluid. The original plan was to have the weapon spray acid over a wide area, but this is only a prototype and has only a narrow spray area.",
      "name": "WeaponText_Weapon120"
    },
    {"type": "string", "value": "Acid Gun", "name": "WeaponName_Weapon121"},
    {
      "type": "string",
      "value": "!     Capacity: 300   \n! Rate of Fire: 60.0/sec\n!       Damage: 15.0    \n!  Reload Time: 3.0sec  \n!        Range: 50.0m\n!     Accuracy: A-        \n\nA special gun that fires strong acid. Rather than spray, this weapon fires a stream of acid directly at the target. Characterized by its improved rate of fire, this weapon can deal incredible damage at close range.",
      "name": "WeaponText_Weapon121"
    },
    {"type": "string", "value": "Acid Shot", "name": "WeaponName_Weapon122"},
    {
      "type": "string",
      "value": "!     Capacity: 20    \n! Rate of Fire: 0.5/sec\n!       Damage: 35.0×40\n!  Reload Time: 5.0sec  \n!        Range: 240.0m \n!     Accuracy: B-        \n\nThe completed Acid Shot model. This special gun fires a spray of strong acid over a wider area than before.",
      "name": "WeaponText_Weapon122"
    },
    {
      "type": "string",
      "value": "Wide Acid Gun",
      "name": "WeaponName_Weapon123"
    },
    {
      "type": "string",
      "value": "!     Capacity: 20    \n! Rate of Fire: 2.0/sec\n!       Damage: 37.0×20\n!  Reload Time: 3.0sec  \n!        Range: 50.0m\n!     Accuracy: A-        \n\nA stronger Acid Gun. This special weapon now fires large volumes of strong acid scattered over a horizontal area.",
      "name": "WeaponText_Weapon123"
    },
    {
      "type": "string",
      "value": "Super Acid Gun",
      "name": "WeaponName_Weapon124"
    },
    {
      "type": "string",
      "value": "!     Capacity: 300   \n! Rate of Fire: 60.0/sec\n!       Damage: 55.0    \n!  Reload Time: 3.0sec  \n!        Range: 100.0m\n!     Accuracy: A-        \n\nThe final Acid Gun model. This weapon uses a new, far more powerful type of acid developed by the science team.",
      "name": "WeaponText_Weapon124"
    },
    {"type": "string", "value": "Burner", "name": "WeaponName_Weapon125"},
    {
      "type": "string",
      "value": "!     Capacity: 60    \n! Rate of Fire: 4.0/sec\n!       Damage: Negligible\n!  Reload Time: 3.0sec  \n\nA gas burner for welding.",
      "name": "WeaponText_Weapon125"
    },
    {
      "type": "string",
      "value": "Flame Thrower",
      "name": "WeaponName_Weapon126"
    },
    {
      "type": "string",
      "value": "!     Capacity: 60    \n! Rate of Fire: 4.0/sec\n!       Damage: Small\n!  Reload Time: 3.0sec  \n\nA high-powered flamethrower developed to exterminate the giant insects. It is an extremely effective weapon in battle against multiple insects or in a narrow space.",
      "name": "WeaponText_Weapon126"
    },
    {
      "type": "string",
      "value": "Flame Thrower α",
      "name": "WeaponName_Weapon127"
    },
    {
      "type": "string",
      "value": "!     Capacity: 180   \n! Rate of Fire: 8.6/sec\n!       Damage: Medium\n!  Reload Time: 3.0sec  \n\nThe most powerful flame thrower available. Obliterates enemies with its deadly flames.",
      "name": "WeaponText_Weapon127"
    },
    {"type": "string", "value": "Flame Cannon", "name": "WeaponName_Weapon128"},
    {
      "type": "string",
      "value": "!     Capacity: 60    \n! Rate of Fire: 8.6/sec\n!       Damage: Medium\n!  Reload Time: 3.0sec  \n\nA flamethrower that has been strengthened for combat.",
      "name": "WeaponText_Weapon128"
    },
    {"type": "string", "value": "Magma Cannon", "name": "WeaponName_Weapon129"},
    {
      "type": "string",
      "value": "!     Capacity: 80    \n! Rate of Fire: 8.6/sec\n!       Damage: Large\n!  Reload Time: 3.0sec  \n\nAn upgraded flame cannon that bathes the enemy in an inferno.",
      "name": "WeaponText_Weapon129"
    },
    {
      "type": "string",
      "value": "C24 Hand Bomb",
      "name": "WeaponName_Weapon130"
    },
    {
      "type": "string",
      "value": "!    Quantity: 5     \n!      Damage: 450.0   \n!  Blast Area: 10.0m      \n! Reload Time: 10.0sec \n\nA special sabotage bomb that is small enough to be thrown. Hold down the attack button to increase throwing distance, then release it to throw. (The bomb's path is indicated by a red line.) \nPress the Zoom/Activate button to detonate.",
      "name": "WeaponText_Weapon130"
    },
    {"type": "string", "value": "C24 Bomb", "name": "WeaponName_Weapon131"},
    {
      "type": "string",
      "value": "!    Quantity: 5     \n!      Damage: 1000.0  \n!  Blast Area: 20.0m      \n! Reload Time: 10.0sec \n\nA special sabotage bomb. This model has high firepower, but is very heavy in exchange, making it impossible to set except right in front of you.\nSet with the Fire button, then detonate with the Zoom/Activate button.",
      "name": "WeaponText_Weapon131"
    },
    {
      "type": "string",
      "value": "C25 Special Bomb",
      "name": "WeaponName_Weapon132"
    },
    {
      "type": "string",
      "value": "!    Quantity: 20    \n!      Damage: 1500.0  \n!  Blast Area: 15.0m      \n! Reload Time: 15.0sec \n\nA special sabotage bomb, several of which can be set and detonated at once.This means firepower is increased several times over, making it a formidable weapon.\nSet with the Fire button, then detonate with the Zoom/Activate button.",
      "name": "WeaponText_Weapon132"
    },
    {"type": "string", "value": "C26 Bomb", "name": "WeaponName_Weapon133"},
    {
      "type": "string",
      "value": "!    Quantity: 5     \n!      Damage: 6000.0  \n!  Blast Area: 30.0m      \n! Reload Time: 10.0sec \n\nA powerful bomb developed in the midst of the Ravager War. It has a large blast area and is terrifyingly powerful.\nSet with the Fire button, then detonate with the Zoom/Activate button.",
      "name": "WeaponText_Weapon133"
    },
    {"type": "string", "value": "C70 Bomb", "name": "WeaponName_Weapon134"},
    {
      "type": "string",
      "value": "!    Quantity: 10    \n!      Damage: 12000.0 \n!  Blast Area: 40.0m      \n! Reload Time: 10.0sec \n\nThe most powerful bomb available. It is rumored to have been developed with Ravager technology, but the truth is unknown. Its incredible power and blast area make it dangerous to use.\nSet with the Fire button, then detonate with the Zoom/Activate button.",
      "name": "WeaponText_Weapon134"
    },
    {"type": "string", "value": "Y10 Impulse", "name": "WeaponName_Weapon135"},
    {
      "type": "string",
      "value": "!    Quantity: 15    \n!      Damage: 15 x 40\n!       Range: 150m\n! Reload Time: 30.0sec \n\nA directional land mine for use against the giant insects. Set with the Fire button, then detonate with the Zoom/Activate button. Upon detonation, a large number of ball bearings launch in one direction, assaulting the enemy.",
      "name": "WeaponText_Weapon135"
    },
    {
      "type": "string",
      "value": "Y10 Wide Impulse",
      "name": "WeaponName_Weapon136"
    },
    {
      "type": "string",
      "value": "!    Quantity: 20    \n!      Damage: 17 x 40\n!       Range: 100m\n! Reload Time: 30.0sec \n\nAn upgraded Y10 Impulse directional land mine. Scatters ball bearings over a wider horizontal area, attacking enemies over a wider field. Multiple bombs can be set before detonation. \nSet with the Fire button, then detonate with the Zoom/Activate button.",
      "name": "WeaponText_Weapon136"
    },
    {"type": "string", "value": "Y11 Impulse", "name": "WeaponName_Weapon137"},
    {
      "type": "string",
      "value": "!    Quantity: 30    \n!      Damage: 20 x 40\n!       Range: 150m\n! Reload Time: 30.0sec \n\nAn upgraded Y10 Impulse model with improved firepower and a greater number that can be set before detonation.\nSet with the Fire button, then detonate with the Zoom/Activate button.",
      "name": "WeaponText_Weapon137"
    },
    {
      "type": "string",
      "value": "Y11 Anti-Aircraft Impulse",
      "name": "WeaponName_Weapon138"
    },
    {
      "type": "string",
      "value": "!    Quantity: 30    \n!      Damage: 40 x 40\n!       Range: 150m\n! Reload Time: 30.0sec \n\nAn upgraded Y11 Impulse model with increased vertical field of fire, making it effective against airborne enemies. Has high firepower and is equally effective against land enemies.\nSet with the Fire button, then detonate with the Zoom/Activate button.",
      "name": "WeaponText_Weapon138"
    },
    {
      "type": "string",
      "value": "Y20 Impulse",
      "name": "WeaponName_BonusWeapon03"
    },
    {
      "type": "string",
      "value": "!    Quantity: 40    \n!      Damage: 20 x 40\n!       Range: 150m\n! Reload Time: 30.0sec \n\nAn upgraded Y11 Impulse model. The number of mines that can be set before detonation is maximized, giving it a much broader application in battle.\nSet with the Fire button, then detonate with the Zoom/Activate button.",
      "name": "WeaponText_BonusWeapon03"
    },
    {"type": "string", "value": "Y21 Impulse", "name": "WeaponName_Weapon139"},
    {
      "type": "string",
      "value": "!    Quantity: 20    \n!      Damage: 125 x 40\n!       Range: 200m\n! Reload Time: 30.0sec \n\nThe final model in the Impulse series. Firepower is pushed to the limit and field of fire is also wider. Scatters ball bearings at enemies in a wide horizontal area.\nSet with the Fire button, then detonate with the Zoom/Activate button.",
      "name": "WeaponText_Weapon139"
    },
    {"type": "string", "value": "ZE-GUN", "name": "WeaponName_Weapon140"},
    {
      "type": "string",
      "value": "!    Quantity: 3          Search Range: 150m\n! Loaded Ammo: 200 shots\n!      Damage: 20.0    \n! Reload Time: 20.0sec \n\nA mounted sentry gun that uses a camera and sensors to track and automatically fire at the enemy. Set with the Fire button and activate with the Zoom/Activate button. The turret will then automatically attack nearby enemies. Developed to combat the Ravagers and giant insects.",
      "name": "WeaponText_Weapon140"
    },
    {"type": "string", "value": "ZER-GUN", "name": "WeaponName_Weapon141"},
    {
      "type": "string",
      "value": "!    Quantity: 2          Search Range: 150m\n! Loaded Ammo: 400 shots\n!      Damage: 4.5     \n! Reload Time: 20.0sec \n\nA ZE-GUN with a higher rate of fire and improved turret rotation that allows it to accurately track airborne and fast-moving enemies. Slightly fewer can be set at one time.\nSet with the Fire button and activate with the Zoom/Activate button. The turret will then automatically attack nearby enemies.",
      "name": "WeaponText_Weapon141"
    },
    {"type": "string", "value": "ZE Sniper", "name": "WeaponName_Weapon142"},
    {
      "type": "string",
      "value": "!    Quantity: 4          Search Range: 800m\n! Loaded Ammo: 20 shots\n!      Damage: 50.0    \n! Reload Time: 20.0sec \n\nA long-range ZE-GUN with high-performance sensors that enable it to spot and take out enemies from longer distances. Power and range are both improved.\nSet with the Fire button and activate with the Zoom/Activate button. The turret will then automatically attack nearby enemies.",
      "name": "WeaponText_Weapon142"
    },
    {
      "type": "string",
      "value": "ZE Launcher",
      "name": "WeaponName_BonusWeapon02"
    },
    {
      "type": "string",
      "value": "!    Quantity: 3          Search Range: 150m\n! Loaded Ammo: 20 shots\n!      Damage: 200.0   \n! Reload Time: 20.0sec \n\nA mounted sentry gun that fires rockets. This weapon has the greatest firepower of all automated turrets.\nSet with the Fire button and activate with the Zoom/Activate button. The turret will then automatically attack nearby enemies.",
      "name": "WeaponText_BonusWeapon02"
    },
    {"type": "string", "value": "ZERA-GUN", "name": "WeaponName_Weapon143"},
    {
      "type": "string",
      "value": "!    Quantity: 2          Search Range: 150m\n! Loaded Ammo: 400 shots\n!      Damage: 40.0    \n! Reload Time: 20.0sec \n\nAn upgraded ZER-GUN that emphasizes rate of fire. Turret rotation is improved, making it possible to attack fast-moving enemies, but fewer can be set at once.\nSet with the Fire button and activate with the Zoom/Activate button. The turret will then automatically attack nearby enemies.",
      "name": "WeaponText_Weapon143"
    },
    {"type": "string", "value": "ZE-GUN10", "name": "WeaponName_Weapon144"},
    {
      "type": "string",
      "value": "!    Quantity: 10         Search Range: 150m\n! Loaded Ammo: 100 shots\n!      Damage: 80.0    \n! Reload Time: 20.0sec \n\nAn upgraded, light-weight ZE-GUN. Enough of these models can be set at once to form a defense perimeter. Basic performance is also high.\nSet with the Fire button and activate with the Zoom/Activate button. The turret will then automatically attack nearby enemies.",
      "name": "WeaponText_Weapon144"
    },
    {"type": "string", "value": "ZEX Launcher", "name": "WeaponName_Weapon145"},
    {
      "type": "string",
      "value": "!    Quantity: 3          Search Range: 150m\n! Loaded Ammo: 40 shots\n!      Damage: 900.0   \n! Reload Time: 20.0sec \n\nA mounted sentry gun that fires high-speed rockets. This weapon has excellent firepower and rotates well. It is considered the epitome of sentry gun technology.\nSet with the Fire button and activate with the Zoom/Activate button. The turret will then automatically attack nearby enemies.",
      "name": "WeaponText_Weapon145"
    },
    {"type": "string", "value": "ZEXR-GUN", "name": "WeaponName_Weapon146"},
    {
      "type": "string",
      "value": "!    Quantity: 3          Search Range: 150m\n! Loaded Ammo: 500 shots\n!      Damage: 70.0    \n! Reload Time: 20.0sec \n\nThe final model in the ZE Gun series. Boasts a high rate of fire and fast turret rotation. Capacity and firepower are also increased, making it the ultimate automated weapon.\nSet with the Fire button and activate with the Zoom/Activate button. The turret will then automatically attack nearby enemies.",
      "name": "WeaponText_Weapon146"
    },
    {
      "type": "string",
      "value": "Firecracker 1",
      "name": "WeaponName_Weapon147"
    },
    {
      "type": "string",
      "value": "!      Damage: 30.0×10\n!        Fuse: Impact\n! Fuse Length: ----\n!  Blast Area: 1.0m       \n\nOfficially known as the Spread Grenade, the Firecracker is basically a smoke ball firework modified into a military weapon. These grenades, each about the size of a Ping-Pong ball, are thrown in clusters at enemies.",
      "name": "WeaponText_Weapon147"
    },
    {
      "type": "string",
      "value": "Firecracker 2",
      "name": "WeaponName_Weapon148"
    },
    {
      "type": "string",
      "value": "!      Damage: 50.0×30\n!        Fuse: Impact\n! Fuse Length: ----\n!  Blast Area: 1.0m       \n\nAn upgraded version of Firecracker 1. Grenade size has been reduced to that of a marble, and considerably more can be thrown at once.",
      "name": "WeaponText_Weapon148"
    },
    {
      "type": "string",
      "value": "Firecracker 3",
      "name": "WeaponName_Weapon149"
    },
    {
      "type": "string",
      "value": "!      Damage: 100.0×30\n!        Fuse: Impact\n! Fuse Length: ----\n!  Blast Area: 2.0m       \n\nA powered-up Firecracker 2. Firepower is a step above the previous model, dealing rather impressive damage when the entire cluster hits.",
      "name": "WeaponText_Weapon149"
    },
    {
      "type": "string",
      "value": "Firecracker 4",
      "name": "WeaponName_Weapon150"
    },
    {
      "type": "string",
      "value": "!      Damage: 90.0×60\n!        Fuse: Impact\n! Fuse Length: ----\n!  Blast Area: 1.0m       \n\nA special Firecracker. Grenades are even smaller, allowing for even more to be thrown at once.",
      "name": "WeaponText_Weapon150"
    },
    {
      "type": "string",
      "value": "Burst Firecracker",
      "name": "WeaponName_Weapon151"
    },
    {
      "type": "string",
      "value": "!      Damage: 320.0×30\n!        Fuse: Impact\n! Fuse Length: ----\n!  Blast Area: 4.0m       \n\nFinally completed, this ultimate firecracker boasts incredible firepower and a larger blast area.",
      "name": "WeaponText_Weapon151"
    },
    {
      "type": "string",
      "value": "P78 Bound Gun",
      "name": "WeaponName_Weapon152"
    },
    {
      "type": "string",
      "value": "!     Capacity: 120   \n! Rate of Fire: 12.0/sec\n!       Damage: 12.0    \n!  Reload Time: 1.5sec  \n!        Range: 220.0m \n!     Accuracy: B         \n\nAn assault rifle based on the AF14. Fires special bullets that rebound off of walls. Firepower and range are considerably higher than with the AF14.",
      "name": "WeaponText_Weapon152"
    },
    {
      "type": "string",
      "value": "P79 Bound Gun",
      "name": "WeaponName_Weapon153"
    },
    {
      "type": "string",
      "value": "!     Capacity: 200   \n! Rate of Fire: 30.0/sec\n!       Damage: 8.0     \n!  Reload Time: 2.5sec  \n!        Range: 240.0m \n!     Accuracy: C         \n\nA special AF16RA model. Fires special bullets that rebound off of walls. The AF16RA's low accuracy can be used to spray bullets over a wide area and take advantage of the special nature of the bullets. Firepower is low compared to the AF16RA, but range is doubled.",
      "name": "WeaponText_Weapon153"
    },
    {
      "type": "string",
      "value": "P80 Bound Gun",
      "name": "WeaponName_Weapon154"
    },
    {
      "type": "string",
      "value": "!     Capacity: 120   \n! Rate of Fire: 15.0/sec\n!       Damage: 28.0    \n!  Reload Time: 1.5sec  \n!        Range: 325.0m \n!     Accuracy: B+        \n\nA special AF19 model. Fires special bullets that rebound off of walls. Fire power is sacrificed for range in order to take full advantage of the special ammunition. Range is more than twice that of the AF19.",
      "name": "WeaponText_Weapon154"
    },
    {
      "type": "string",
      "value": "P89 Bound Gun",
      "name": "WeaponName_Weapon155"
    },
    {
      "type": "string",
      "value": "!     Capacity: 30    \n! Rate of Fire: 12.0/sec\n!       Damage: 200.0   \n!  Reload Time: 3.0sec  \n!        Range: 90.0m  \n!     Accuracy: B         \n\nAn assault rifle that fires extremely slow bullets that rebound off walls. Shots are slow, but their power is incredible.",
      "name": "WeaponText_Weapon155"
    },
    {
      "type": "string",
      "value": "PX50 Bound Shot",
      "name": "WeaponName_BonusWeapon04"
    },
    {
      "type": "string",
      "value": "!     Capacity: 8     \n! Rate of Fire: 1.0/sec\n!       Damage: 40.0×50\n!  Reload Time: 6.0sec  \n!        Range: 540.0m \n!     Accuracy: D         \n\nA special version of the Governor 50 shotgun. This newly developed weapon fires special bullets that rebound off of walls. Additionally, range is exceedingly long for a shotgun. You might want to try using it in a small space once...",
      "name": "WeaponText_BonusWeapon04"
    }
  ],
  "version": 249503767
}