{
  "endian": "LE",
  "variables": [
    {
      "type": "string",
      "name": "AimAnimation",
      "value": "aim"
    },
    {
      "type": "int",
      "name": "AmmoAlive",
      "value": 300
    },
    {
      "type": "string",
      "name": "AmmoClass",
      "options": [
        "LightningBullet01",
        "LaserBullet01",
        "LaserBullet02",
        "LaserBullet03",
        "FlameBullet01",
        "FlameBullet02",
        "SpiderStringBullet01",
        "SpiderStringBullet02",
        "ShockWaveBullet01",
        "SlashWaveBullet01",
        "HomingLaserBullet01",
        "BeamBullet01",
        "DecoyBullet01",
        "NeedleBullet01",
        "BarrierBullet01",
        "ClusterBullet01",
        "AcidBullet01",
        "NapalmBullet01",
        "GrenadeBullet01",
        "MissileBullet01",
        "MissileBullet02",
        "RocketBullet01",
        "RocketBullet02",
        "SolidBullet01",
        "SolidBullet02",
        "SmokeCandleBullet01",
        "ShieldBashBullet01",
        "SentryGunBullet01",
        "TargetMarkerBullet01",
        "SupportUnitBullet01",
        "PileBunkerBullet01",
        "PlasmaBullet01"
      ],
      "value": "MissileBullet01"
    },
    {
      "type": "ptr",
      "name": "AmmoColor",
      "value": [
        {
          "type": "float",
          "name": "Red",
          "value": 1
        },
        {
          "type": "float",
          "name": "Green",
          "value": 1
        },
        {
          "type": "float",
          "name": "Blue",
          "value": 1
        },
        {
          "type": "float",
          "name": "Alpha",
          "value": 1
        }
      ]
    },
    {
      "type": "ptr",
      "name": "AmmoCount",
      "value": [
        {
          "type": "int",
          "value": 3
        },
        {
          "type": "int",
          "value": 0
        },
        {
          "type": "int",
          "value": 0
        },
        {
          "type": "int",
          "value": 8
        },
        {
          "type": "float",
          "value": 0.5
        },
        {
          "type": "float",
          "value": 1.5
        }
      ]
    },
    {
      "type": "ptr",
      "name": "AmmoDamage",
      "value": [
        {
          "type": "float",
          "value": 416
        },
        {
          "type": "int",
          "value": 8
        },
        {
          "type": "int",
          "value": 1
        },
        {
          "type": "int",
          "value": 8
        },
        {
          "type": "float",
          "value": 0.5
        },
        {
          "type": "float",
          "value": 0.5
        }
      ]
    },
    {
      "type": "ptr",
      "name": "AmmoDamageReduce",
      "value": [
        {
          "type": "float",
          "value": 1
        },
        {
          "type": "float",
          "value": 1
        }
      ]
    },
    {
      "type": "ptr",
      "name": "AmmoExplosion",
      "value": [
        {
          "type": "float",
          "value": 11
        },
        {
          "type": "int",
          "value": 32
        },
        {
          "type": "int",
          "value": 5
        },
        {
          "type": "int",
          "value": 8
        },
        {
          "type": "float",
          "value": 0.5
        },
        {
          "type": "float",
          "value": 0.5
        }
      ]
    },
    {
      "type": "float",
      "name": "AmmoGravityFactor",
      "value": 0.5
    },
    {
      "type": "float",
      "name": "AmmoHitImpulseAdjust",
      "value": 1
    },
    {
      "type": "ptr",
      "name": "AmmoHitSe",
      "value": [
        {
          "type": "int",
          "value": 0
        },
        {
          "type": "string",
          "value": "common_damages_explode_S"
        },
        {
          "type": "float",
          "value": 1
        },
        {
          "type": "float",
          "value": 1
        },
        {
          "type": "float",
          "value": 1
        },
        {
          "type": "float",
          "value": 200
        }
      ]
    },
    {
      "type": "float",
      "name": "AmmoHitSizeAdjust",
      "value": 1
    },
    {
      "type": "int",
      "name": "AmmoIsPenetration",
      "value": 0
    },
    {
      "type": "string",
      "name": "AmmoModel",
      "value": "app:/WEAPON/bullet_rocket.rab"
    },
    {
      "type": "float",
      "name": "AmmoOwnerMove",
      "value": 0
    },
    {
      "type": "float",
      "name": "AmmoSize",
      "value": 1.5
    },
    {
      "type": "float",
      "name": "AmmoSpeed",
      "value": 0.20000000298023224
    },
    {
      "type": "ptr",
      "name": "Ammo_CustomParameter",
      "value": [
        {
          "type": "int",
          "value": 0
        },
        {
          "type": "int",
          "value": 1
        },
        {
          "type": "int",
          "value": 100
        },
        {
          "type": "ptr",
          "value": [
            {
              "type": "float",
              "value": 0
            },
            {
              "type": "float",
              "value": 0
            },
            {
              "type": "float",
              "value": -0.05000000074505806
            }
          ]
        },
        {
          "type": "float",
          "value": 0.03999999910593033
        },
        {
          "type": "float",
          "value": 0
        },
        {
          "type": "float",
          "value": 10
        },
        {
          "type": "ptr",
          "value": [
            {
              "type": "int",
              "value": 15
            },
            {
              "type": "float",
              "value": 0.949999988079071
            }
          ]
        },
        {
          "type": "int",
          "value": 0
        },
        {
          "type": "int",
          "value": 0
        },
        {
          "type": "ptr",
          "value": null
        },
        {
          "type": "ptr",
          "value": [
            {
              "type": "int",
              "value": 0
            },
            {
              "type": "string",
              "value": "weapon_Ranger_ML_go_Medium"
            },
            {
              "type": "float",
              "value": 0.4000000059604645
            },
            {
              "type": "float",
              "value": 0.6674200296401978
            },
            {
              "type": "float",
              "value": 1
            },
            {
              "type": "float",
              "value": 100
            }
          ]
        }
      ]
    },
    {
      "type": "ptr",
      "name": "Ammo_EquipVoice",
      "value": null
    },
    {
      "type": "float",
      "name": "AngleAdjust",
      "value": 0
    },
    {
      "type": "string",
      "name": "BaseAnimation",
      "value": "shoulder"
    },
    {
      "type": "string",
      "name": "ChangeAnimation",
      "value": "shoulder_change1"
    },
    {
      "type": "ptr",
      "name": "EnergyChargeRequire",
      "value": [
        {
          "type": "float",
          "value": -1
        },
        {
          "type": "float",
          "value": -1
        }
      ]
    },
    {
      "type": "ptr",
      "name": "ExtPrams",
      "value": [
        {
          "type": "float",
          "value": 1
        }
      ]
    },
    {
      "type": "ptr",
      "name": "FireAccuracy",
      "value": [
        {
          "type": "float",
          "value": 0.009999999776482582
        },
        {
          "type": "int",
          "value": 13
        },
        {
          "type": "int",
          "value": 2
        },
        {
          "type": "int",
          "value": 5
        },
        {
          "type": "float",
          "value": 3
        },
        {
          "type": "float",
          "value": 1
        }
      ]
    },
    {
      "type": "int",
      "name": "FireBurstCount",
      "value": 1
    },
    {
      "type": "int",
      "name": "FireBurstInterval",
      "value": 0
    },
    {
      "type": "int",
      "name": "FireCondition",
      "value": 0
    },
    {
      "type": "int",
      "name": "FireCount",
      "value": 1
    },
    {
      "type": "ptr",
      "name": "FireInterval",
      "value": [
        {
          "type": "int",
          "value": 45
        },
        {
          "type": "int",
          "value": 25
        },
        {
          "type": "int",
          "value": 4
        },
        {
          "type": "int",
          "value": 5
        },
        {
          "type": "float",
          "value": 0.5
        },
        {
          "type": "float",
          "value": 0.5
        }
      ]
    },
    {
      "type": "ptr",
      "name": "FireLoadSe",
      "value": null
    },
    {
      "type": "float",
      "name": "FireRecoil",
      "value": 0.4000000059604645
    },
    {
      "type": "ptr",
      "name": "FireSe",
      "value": [
        {
          "type": "int",
          "value": 0
        },
        {
          "type": "string",
          "name": "SoundName",
          "value": "e5w_RLnew_SMAW-FA01mk2"
        },
        {
          "type": "float",
          "value": 1
        },
        {
          "type": "float",
          "value": 1
        },
        {
          "type": "float",
          "value": 2
        },
        {
          "type": "float",
          "value": 25
        }
      ]
    },
    {
      "type": "int",
      "name": "FireSpreadType",
      "value": 0
    },
    {
      "type": "float",
      "name": "FireSpreadWidth",
      "value": 0
    },
    {
      "type": "int",
      "name": "FireType",
      "value": 0
    },
    {
      "type": "ptr",
      "name": "FireVector",
      "value": null
    },
    {
      "type": "ptr",
      "name": "LockonAngle",
      "value": [
        {
          "type": "float",
          "value": 0.30000001192092896
        },
        {
          "type": "float",
          "value": 0.30000001192092896
        }
      ]
    },
    {
      "type": "int",
      "name": "LockonFailedTime",
      "value": 0
    },
    {
      "type": "int",
      "name": "LockonHoldTime",
      "value": 0
    },
    {
      "type": "float",
      "name": "LockonRange",
      "value": 0
    },
    {
      "type": "int",
      "name": "LockonTargetType",
      "value": 0
    },
    {
      "type": "int",
      "name": "LockonTime",
      "value": 0
    },
    {
      "type": "int",
      "name": "LockonType",
      "value": 0
    },
    {
      "type": "int",
      "name": "Lockon_AutoTimeOut",
      "value": 1
    },
    {
      "type": "int",
      "name": "Lockon_DistributionType",
      "value": 0
    },
    {
      "type": "int",
      "name": "Lockon_FireEndToClear",
      "value": 1
    },
    {
      "type": "ptr",
      "name": "ModelConstraint",
      "value": [
        {
          "type": "string",
          "value": "arms_r"
        }
      ]
    },
    {
      "type": "string",
      "name": "MuzzleFlash",
      "value": "MuzzleSmoke01"
    },
    {
      "type": "ptr",
      "name": "MuzzleFlash_CustomParameter",
      "value": [
        {
          "type": "int",
          "value": 1
        },
        {
          "type": "float",
          "value": 0.125
        },
        {
          "type": "ptr",
          "value": [
            {
              "type": "float",
              "value": 1
            },
            {
              "type": "float",
              "value": 1
            },
            {
              "type": "float",
              "value": 1
            },
            {
              "type": "float",
              "value": 0.5
            }
          ]
        },
        {
          "type": "float",
          "value": 0.05000000074505806
        },
        {
          "type": "ptr",
          "value": [
            {
              "type": "float",
              "value": 0
            },
            {
              "type": "float",
              "value": 0
            },
            {
              "type": "float",
              "value": -1.600000023841858
            }
          ]
        }
      ]
    },
    {
      "type": "string",
      "name": "ReloadAnimation",
      "value": "shoulder_reload1"
    },
    {
      "type": "float",
      "name": "ReloadInit",
      "value": 1
    },
    {
      "type": "ptr",
      "name": "ReloadTime",
      "value": [
        {
          "type": "int",
          "value": 90
        },
        {
          "type": "int",
          "value": 21
        },
        {
          "type": "int",
          "value": 3
        },
        {
          "type": "int",
          "value": 5
        },
        {
          "type": "float",
          "value": 1
        },
        {
          "type": "float",
          "value": 0.5
        }
      ]
    },
    {
      "type": "int",
      "name": "ReloadType",
      "value": 0
    },
    {
      "type": "float",
      "name": "SecondaryFire_Parameter",
      "value": 2
    },
    {
      "type": "int",
      "name": "SecondaryFire_Type",
      "options": {
        "None": 0,
        "Zoom": 1,
        "Activate": 2,
        "Activate and Reload": 3,
        "Jumpjets (Fencer)": 4,
        "Dash (Fencer)": 5,
        "Shield Reflect (Fencer)": 6
      },
      "value": 1
    },
    {
      "type": "ptr",
      "name": "ShellCase",
      "value": [
        {
          "type": "string",
          "value": ""
        },
        {
          "type": "string",
          "value": ""
        },
        {
          "type": "int",
          "value": 0
        }
      ]
    },
    {
      "type": "ptr",
      "name": "ShellCaseDischargeSe",
      "value": null
    },
    {
      "type": "ptr",
      "name": "ShellCase_CustomParameter",
      "value": null
    },
    {
      "type": "ptr",
      "name": "Sight_animation_model",
      "value": [
        {
          "type": "ptr",
          "value": [
            {
              "type": "string",
              "value": "app:/HUD/sight02.rab"
            },
            {
              "type": "string",
              "value": "sight02.mdb"
            }
          ]
        },
        {
          "type": "int",
          "value": 0
        },
        {
          "type": "int",
          "value": 0
        }
      ]
    },
    {
      "type": "string",
      "name": "WeaponIcon",
      "value": "app:/weapon/icon/stingray.dds"
    },
    {
      "type": "ptr",
      "name": "animation_model",
      "value": [
        {
          "type": "ptr",
          "value": [
            {
              "type": "string",
              "value": "app:/Weapon/s_rocket_stingray01.rab"
            },
            {
              "type": "string",
              "value": "s_rocket_stingray01.mdb"
            }
          ]
        },
        {
          "type": "int",
          "value": 0
        },
        {
          "type": "extra",
          "value": {
            "type": "MAB\u0000",
            "data": "TUFCAA8AAAADAAAAAwAAAAUANAAkAAAAfAAAAIAAAADwAAAAAAABADwAAAABAAEAXAAAAAIAAAB8AAAA8AAAAPwAAAACAAAAkAAAAKAAAACAAAAAAAAAANAAAAD2AAAA/AAAAAIAAACwAAAAoAAAAMAAAAAAAAAA0AAAALq6uroAAAAAAAAAAAAAAAAAAIA/AAAAACUGAT4xCCw/AACAP83MzDzNzMw8zczMPAAAgD/Zzvc9AAAAAFg5ND4AAIA/wg/zu+l3br46ekVAAACAP1NHTwACAQAAAAAAACAAAAAAAAAAIAAAAAAAAAAgAAAAMAAxAAAASQBLAAAAcwBfAHIAbwBjAGsAZQB0AF8AcwB0AGkAbgBnAHIAYQB5ADAAMQAAAA=="
          }
        }
      ]
    },
    {
      "type": "ptr",
      "name": "custom_parameter",
      "value": [
        {
          "type": "string",
          "value": "shoulder_recoil1"
        },
        {
          "type": "int",
          "value": 0
        },
        {
          "type": "int",
          "value": 0
        },
        {
          "type": "float",
          "value": 1
        }
      ]
    },
    {
      "type": "string",
      "name": "name.cn",
      "value": "承諾者Ｍ４１"
    },
    {
      "type": "string",
      "name": "name.en",
      "value": "Grant M41"
    },
    {
      "type": "string",
      "name": "name.ja",
      "value": "グラントＭ４１"
    },
    {
      "type": "string",
      "name": "name.kr",
      "value": "그런트 M41"
    },
    {
      "type": "ptr",
      "name": "resource",
      "value": [
        {
          "type": "string",
          "name": "path",
          "value": "app:/WEAPON/bullet_rocket.rab"
        }
      ]
    },
    {
      "type": "int",
      "name": "use_underground",
      "value": 1
    },
    {
      "type": "string",
      "name": "xgs_scene_object_class",
      "value": "Weapon_BasicShoot"
    }
  ],
  "meta": {
    "help": "For examples of these values, open WEAPONTABLE.SGO and WEAPONTEXT.SGO",
    "id": null,
    "level": null,
    "category": null,
    "unlockState": null,
    "dropRateModifier": null,
    "description": null
  }
}