{
  "format": "DSGO",
  "endian": "LE",
  "data": {
    "xgs_scene_object_class": "Weapon_Accessory",
    "custom_parameter": [
      [[15, 1.149999976158142], [100, 1.2000000476837158], [103, 1]]
    ],
    "use_underground": 1,
    "FireCondition": 0,
    "name.ja": "ハイブリッドプロテクター",
    "name.en": "Hybrid Protector",
    "name.cn": "雙機能防護衣",
    "name.kr": "하이브리드 프로텍터",
    "name.sc": "双机能防护衣",
    "WeaponIcon": "app:/weapon/icon/none",
    "BaseAnimation": "none",
    "AimAnimation": "",
    "ChangeAnimation": "",
    "ReloadAnimation": "",
    "AmmoCount": 0,
    "EnergyChargeRequire": [-1, -1],
    "ReloadType": 0,
    "ReloadInit": 1,
    "ReloadTime": -1,
    "AngleAdjust": 0,
    "LockonType": 0,
    "LockonTargetType": 0,
    "Lockon_DistributionType": 0,
    "Lockon_FireEndToClear": 1,
    "Lockon_AutoTimeOut": 1,
    "LockonRange": 0,
    "LockonAngle": [0, 0],
    "LockonTime": 0,
    "LockonFailedTime": 0,
    "LockonHoldTime": 0,
    "FireType": 0,
    "FireSpreadType": 0,
    "FireSpreadWidth": 0,
    "FireCount": 1,
    "FireInterval": 1,
    "FireBurstCount": 0,
    "FireBurstInterval": 0,
    "FireAccuracy": 0,
    "FireRecoil": 0,
    "FireVector": null,
    "FireSe": null,
    "FireLoadSe": null,
    "ShellCaseDischargeSe": null,
    "SecondaryFire_Type": 0,
    "SecondaryFire_Parameter": [0],
    "AmmoClass": "",
    "AmmoModel": 0,
    "AmmoSpeed": 0,
    "AmmoOwnerMove": 0,
    "AmmoGravityFactor": 0,
    "AmmoAlive": 0,
    "AmmoDamage": 0,
    "AmmoDamageReduce": [1, 1],
    "AmmoExplosion": 0,
    "AmmoIsPenetration": 0,
    "AmmoSize": 1,
    "AmmoHitSizeAdjust": 1,
    "AmmoHitImpulseAdjust": 1,
    "AmmoColor": [1, 1, 1, 1],
    "Ammo_CustomParameter": null,
    "Ammo_EquipVoice": null,
    "AmmoHitSe": null,
    "MuzzleFlash": "",
    "MuzzleFlash_CustomParameter": null,
    "ShellCase": ["", "", 0],
    "ShellCase_CustomParameter": null,
    "ExtPrams": [1]
  },
  "strings": [
    "AmmoExplosion",
    "LockonTargetType",
    "BaseAnimation",
    "AmmoColor",
    "LockonAngle",
    "AimAnimation",
    "WeaponIcon",
    "Lockon_AutoTimeOut",
    "ReloadType",
    "MuzzleFlash",
    "AmmoAlive",
    "FireVector",
    "FireType",
    "AmmoClass",
    "AmmoDamageReduce",
    "AmmoDamage",
    "AmmoGravityFactor",
    "AmmoCount",
    "SecondaryFire_Type",
    "AmmoHitImpulseAdjust",
    "AmmoHitSe",
    "AmmoHitSizeAdjust",
    "AmmoIsPenetration",
    "AmmoModel",
    "AmmoOwnerMove",
    "FireCondition",
    "AmmoSize",
    "AmmoSpeed",
    "ReloadInit",
    "Ammo_CustomParameter",
    "LockonTime",
    "Ammo_EquipVoice",
    "AngleAdjust",
    "name.cn",
    "SecondaryFire_Parameter",
    "LockonFailedTime",
    "ChangeAnimation",
    "FireAccuracy",
    "EnergyChargeRequire",
    "ReloadTime",
    "ExtPrams",
    "FireBurstCount",
    "LockonRange",
    "FireBurstInterval",
    "FireCount",
    "FireInterval",
    "FireLoadSe",
    "FireRecoil",
    "FireSe",
    "FireSpreadType",
    "FireSpreadWidth",
    "LockonHoldTime",
    "LockonType",
    "ShellCase_CustomParameter",
    "Lockon_DistributionType",
    "name.kr",
    "Lockon_FireEndToClear",
    "MuzzleFlash_CustomParameter",
    "ReloadAnimation",
    "ShellCase",
    "ShellCaseDischargeSe",
    "custom_parameter",
    "name.en",
    "name.ja",
    "name.sc",
    "use_underground",
    "xgs_scene_object_class",
    "Weapon_Accessory",
    "ハイブリッドプロテクター",
    "Hybrid Protector",
    "雙機能防護衣",
    "하이브리드 프로텍터",
    "none",
    "双机能防护衣",
    "app:/weapon/icon/none",
    ""
  ]
}